Workbook

Sheet Read Me
A1: Workday Worker Fields Handbook
A2: Built from Worker_PBO.xlsx (primary business object fields) and Worker_RBO.xlsx (related business objects).
A4: At a glance
A5: Total Worker fields (PBO) | B5: =COUNTA('All Worker Fields'!A:A)-1 -> 3254
A6: Workday Delivered fields | B6: =COUNTIF('All Worker Fields'!C:C,"Workday Delivered") -> 2835
A7: Calculated fields | B7: =COUNTIF('All Worker Fields'!C:C,"Calculated") -> 408
A8: Custom fields | B8: =COUNTIF('All Worker Fields'!C:C,"Custom Field") -> 11
A9: Related business objects (RBO) | B9: =COUNTA('Related Objects'!A5:A2000) -> 635
A10: Curated common fields in this handbook | B10: =COUNTA('Common Fields'!C:C)-1 -> 178
A12: Tabs
A13: Common Fields | B13: The handbook: 178 commonly used Worker fields in 11 sections, each with type, related object, description, prompts, usage area and a practical tip. Start here.
A14: Field Types | B14: What each field type means and how to use it in reports and calculated fields, with live counts from the full catalog.
A15: Categories | B15: Every PBO category with its field count, to help you browse the full catalog.
A16: Related Objects | B16: All 635 related business objects from the RBO file, with the number of Worker fields that link to each and example linking fields.
A17: All Worker Fields | B17: The complete PBO catalog (3,254 fields), filterable. Rows marked "Yes" in the Common column are in the handbook.
A19: Column guide
A20: Field Name | B20: Field name exactly as it appears in Workday report writer and calculated fields.
A21: Field Type | B21: Data type returned (see the Field Types tab). Instance types return objects you can drill into.
A22: Related Business Object | B22: The object an instance field returns. Blank for simple types (Text, Date, Numeric, etc.).
A23: Field Source | B23: Workday Delivered, Calculated (tenant calculated field) or Custom Field.
A24: Built-in Prompts | B24: Parameters the field needs (for example As Of, End Date). Fields with prompts behave differently in reports.
A25: Category | B25: Workday field category; useful in the report-writer field picker.
A26: Authorized Usage | B26: Where the field may be used (Default Areas = general reporting; others such as Benefits Eligibility or Security Attribute are restricted contexts).
A27: Handbook Tip | B27: Practical guidance written for this handbook (not from the source files).
A29: Note | B29: Field names, types, descriptions, prompts, categories and usage come from your PBO/RBO exports. Section groupings and tips are editorial guidance; check field behavior in your tenant before using it in production reports. Sensitive fields (personal, demographic, national IDs, compensation) are subject to domain security.

Sheet Common Fields
A1: Commonly Used Worker Fields
A2: Curated from the Worker PBO. Filter by Section or Field Type; the Handbook Tip column is practical guidance.
A4: # | B4: Section | C4: Field Name | D4: Field Type | E4: Related Business Object | F4: Description | G4: Field Source | H4: Built-in Prompts | I4: Category | J4: Authorized Usage | K4: Handbook Tip
A5: 1 | B5: 1. Identity & Name | C5: Worker | D5: Self referencing instance | E5: Worker | F5: Identifies the worker and enables you to view and access related details and actions on the worker. | G5: Workday Delivered | I5: Benefits Eligibility | J5: Security Attribute - System User | K5: The worker instance itself. Use as the first column in most reports; drill into it for any related data.
A6: 2 | B6: 1. Identity & Name | C6: Employee ID | D6: Text | F6: The Employee ID or Contingent Worker ID for the worker. | G6: Workday Delivered | I6: Benefits Eligibility | J6: Benefits Eligibility | K6: Primary key for integrations and matching across systems. Text, so keep leading zeros.
A7: 3 | B7: 1. Identity & Name | C7: Legal Name | D7: Single instance | E7: Global Name Interface | F7: The current legal name of a worker, without an effective date. It displays in the General Name Display Format set in Edit Tenant Setup - System task. Use the Legal Name (Effective Dated) report field if you need the effective date of the ~worker’s~ legal name. | G7: Workday Delivered | I7: Name | J7: Default Areas | K7: Official name, used on payroll, tax and legal documents.
A8: 4 | B8: 1. Identity & Name | C8: Legal Name - First Name | D8: Text | F8: The worker's legal first or given name. | G8: Workday Delivered | I8: Name | J8: Default Areas | K8: Use the split name parts for mail-merge and file layouts.
A9: 5 | B9: 1. Identity & Name | C9: Legal Name - Middle Name | D9: Text | F9: The worker's legal middle name. | G9: Workday Delivered | I9: Name | J9: Default Areas
A10: 6 | B10: 1. Identity & Name | C10: Legal Name - Last Name | D10: Text | F10: The worker's legal family name. | G10: Workday Delivered | I10: Name | J10: Default Areas | K10: Sort or group directories by this field.
A11: 7 | B11: 1. Identity & Name | C11: Full Legal Name | D11: Text | F11: Returns Full Legal Name in Long Name Format. For Malaysia and Singapore returns Full Name (Full Person Name attribute of Global Person Name class) if defined. | G11: Workday Delivered | I11: Name | J11: Default Areas | K11: Single text string of the full legal name; handy for exports.
A12: 8 | B12: 1. Identity & Name | C12: Preferred Name | D12: Single instance | E12: Global Name Interface | F12: Returns the worker's preferred name. | G12: Workday Delivered | I12: Name | J12: Default Areas | K12: Name the worker chooses to be called; use for directories, org charts and emails.
A13: 9 | B13: 1. Identity & Name | C13: Preferred Name - First Name | D13: Text | F13: The worker's preferred first or given name. | G13: Workday Delivered | I13: Name | J13: Default Areas
A14: 10 | B14: 1. Identity & Name | C14: Preferred Name - Last Name | D14: Text | F14: The worker's preferred family name. | G14: Workday Delivered | I14: Name | J14: Default Areas
A15: 11 | B15: 1. Identity & Name | C15: User Name | D15: Text | F15: Contains the User Name associated with the Workday Account | G15: Workday Delivered | I15: Workday Account | J15: Default Areas | K15: Workday account sign-in name; useful for SSO and provisioning checks.
A16: 12 | B16: 1. Identity & Name | C16: Universal Id | D16: Text | F16: Universal Id for the Worker | G16: Workday Delivered | I16: Basic Bio | J16: Default Areas | K16: Cross-system person identifier, when your tenant uses Universal ID.
A17: 13 | B17: 1. Identity & Name | C17: Person | D17: Single instance | E17: Person | F17: The person who has this role. | G17: Workday Delivered | I17: Roles | J17: Default Areas | K17: Links to the underlying Person; same person can hold multiple worker records.
A18: 14 | B18: 1. Identity & Name | C18: Photo | D18: Single instance | E18: Image | F18: Returns the photo for the worker. | G18: Workday Delivered | I18: Basic Bio | J18: Default Areas | K18: Worker photo image; used in org charts and directories.
A19: 15 | B19: 1. Identity & Name | C19: Previous Worker ID | D19: Text | F19: Answer for the previous worker ID question on the job application. | G19: Workday Delivered | I19: Recruiting | J19: Default Areas | K19: ID from a previous record (for example a rehire or conversion); helps reconcile history.
A20: 16 | B20: 2. Worker Status & Classification | C20: Worker Type | D20: Single instance | E20: Worker Type | F20: The worker type (employee or contingent worker) for a worker. | G20: Workday Delivered | I20: Employment | J20: Security Attribute - System User | K20: Employee vs. Contingent Worker. The most common top-level report filter.
A21: 17 | B21: 2. Worker Status & Classification | C21: Employee Type | D21: Multi-instance | E21: Employee Type | F21: The employee type for the employee's primary position. | G21: Workday Delivered | I21: Benefits Eligibility | J21: Benefits Eligibility | K21: Regular, Temporary, Fixed Term and so on (tenant-configured). Multi-instance: one value per position.
A22: 18 | B22: 2. Worker Status & Classification | C22: Contingent Worker Type | D22: Single instance | E22: Contingent Worker Type | F22: Contains the type of contingent worker. | G22: Workday Delivered | I22: Benefits Eligibility | J22: Security Attribute - System User | K22: Contractor, Consultant, Vendor and so on, for contingent workers.
A23: 19 | B23: 2. Worker Status & Classification | C23: Worker is Contingent Worker | D23: Boolean | F23: Returns true if this Worker is a Contingent Worker. | G23: Workday Delivered | I23: Benefits Eligibility | J23: Benefits Eligibility | K23: Boolean shortcut for filters and calculated fields.
A24: 20 | B24: 2. Worker Status & Classification | C24: Active Status (Date As Of) | D24: Boolean | F24: Returns 'Yes' if the worker is active as of the Date As Of calculated field. Excludes workers who are on certain types of leave or who are terminated. | G24: Workday Delivered | I24: Job & Position | J24: Default Areas | K24: True when the worker is active as of the report's effective date.
A25: 21 | B25: 2. Worker Status & Classification | C25: Terminated | D25: Boolean | F25: True if worker's primary position is terminated or if the contract has ended. Use for business process condition rules but not for custom reports. Use Terminated (based on report date) for custom reports. | G25: Workday Delivered | I25: Employment | J25: Security Attribute - System User | K25: Boolean; combine with Termination Date for leaver reporting.
A26: 22 | B26: 2. Worker Status & Classification | C26: On Leave | D26: Boolean | F26: Identifies if an employee is on leave. | G26: Workday Delivered | I26: Benefits Eligibility | J26: Security Attribute - System User | K26: True while the worker is on an approved leave of absence.
A27: 23 | B27: 2. Worker Status & Classification | C27: Is Manager | D27: Boolean | F27: Identifies if the worker has a manager role. | G27: Workday Delivered | I27: Employment | J27: Security Attribute - System User | K27: True when the worker manages a supervisory organization.
A28: 24 | B28: 2. Worker Status & Classification | C28: Is Rehire | D28: Boolean | F28: Returns "Yes" if the processing worker is a rehire at the processing moment. A worker is considered to be a rehire if they have been hired more than once in the past and they are not terminated. | G28: Workday Delivered | I28: Job & Position | J28: Default Areas | K28: Flags workers who were previously employed.
A29: 25 | B29: 2. Worker Status & Classification | C29: Is Retiree | D29: Boolean | F29: Indicates whether a worker is a retiree. | G29: Workday Delivered | I29: Benefits Eligibility | J29: Benefits Eligibility | K29: Flags workers in a retiree status.
A30: 26 | B30: 2. Worker Status & Classification | C30: Time Type | D30: Single instance | E30: Time Type | F30: The position time type for the worker's primary position. | G30: Workday Delivered | I30: Employment | J30: Security Attribute - System User | K30: Full time or Part time.
A31: 27 | B31: 2. Worker Status & Classification | C31: Pay Rate Type | D31: Single instance | E31: Pay Rate Type | F31: The pay rate type for an employee's position and is used by payroll. | G31: Workday Delivered | I31: Benefits Eligibility | J31: Security Attribute - System User | K31: Salary vs. Hourly.
A32: 28 | B32: 2. Worker Status & Classification | C32: Exempt | D32: Boolean | F32: Returns "Yes" if the worker's primary position is exempt from overtime. | G32: Workday Delivered | I32: Employment | J32: Security Attribute - System User | K32: FLSA exempt flag (US). Use for overtime eligibility reporting.
A33: 29 | B33: 2. Worker Status & Classification | C33: FTE | D33: Numeric | F33: The full time equivalent for the worker's primary position. | G33: Workday Delivered | I33: Benefits Eligibility | J33: Benefits Eligibility | K33: Full-time-equivalent value of the primary position (for example 1.0 or 0.5).
A34: 30 | B34: 2. Worker Status & Classification | C34: Scheduled Weekly Hours | D34: Numeric | F34: The weekly hours for the worker's primary position. This is used in the Full Time Equivalent calculation: Scheduled Weekly Hours / Standard Weekly Hours. | G34: Workday Delivered | I34: Benefits Eligibility | J34: Benefits Eligibility | K34: Hours the worker is scheduled to work each week.
A35: 31 | B35: 2. Worker Status & Classification | C35: Default Weekly Hours | D35: Numeric | F35: The standard hours for the worker's primary position. Usually this is equal to the location standard hours but can be overridden at the position level. This is used in the calculation for Full Time Equivalent: Scheduled Weekly Hours / Standard Weekly Hours. | G35: Workday Delivered | I35: Job & Position | J35: Default Areas | K35: Standard full-time hours for the location or position; compare with scheduled hours.
A36: 32 | B36: 3. Key Dates & Service | C36: Hire Date | D36: Date | F36: The worker's most recent hire date. This report field cannot be effective dated. | G36: Workday Delivered | I36: Benefits Eligibility | J36: Security Attribute - System User | K36: Most recent hire date. Basis for most service calculations.
A37: 33 | B37: 3. Key Dates & Service | C37: Original Hire Date | D37: Date | F37: The date when the employee was first hired. | G37: Workday Delivered | I37: Benefits Eligibility | J37: Benefits Eligibility | K37: First-ever hire date; differs from Hire Date for rehires.
A38: 34 | B38: 3. Key Dates & Service | C38: Continuous Service Date | D38: Date | F38: Employee service date taking into account breaks in service. | G38: Workday Delivered | I38: Employment | J38: Benefits Eligibility | K38: Date used for continuous service and benefits eligibility.
A39: 35 | B39: 3. Key Dates & Service | C39: Seniority Date | D39: Date | F39: The seniority date for the worker. | G39: Workday Delivered | I39: Benefits Eligibility | J39: Benefits Eligibility | K39: Used for seniority-based rules (for example unions and layoffs).
A40: 36 | B40: 3. Key Dates & Service | C40: Company Service Date | D40: Date | F40: Company Service Date for the Worker. | G40: Workday Delivered | I40: Benefits Eligibility | J40: Benefits Eligibility | K40: Service date at the current company.
A41: 37 | B41: 3. Key Dates & Service | C41: Probation End Date | D41: Date | F41: The probation period end date for the worker's primary position. | G41: Workday Delivered | H41: Effective Date | I41: Probation Period | J41: Default Areas | K41: End of the probation period.
A42: 38 | B42: 3. Key Dates & Service | C42: Last Promotion Date | D42: Date | F42: Returns most recent promotion event for worker's primary job. | G42: Workday Delivered | I42: Job & Position | J42: Default Areas | K42: Date of the most recent promotion.
A43: 39 | B43: 3. Key Dates & Service | C43: Effective Date for Current Position | D43: Date | F43: The effective date of the last completed staffing business process or reorganization for the current primary position held by the worker. | G43: Workday Delivered | I43: Job & Position | J43: Default Areas | K43: When the worker started the current position.
A44: 40 | B44: 3. Key Dates & Service | C44: Termination Date | D44: Date | F44: The Effective Date of the worker's last termination. Doesn't include future-dated terminations or terminations with a rehire on the next day. To include terminations with a next-day rehire, use the Termination Date - All report field. | G44: Workday Delivered | I44: Employment | J44: Default Areas | K44: Effective termination date (blank for active workers).
A45: 41 | B45: 3. Key Dates & Service | C45: Last Day of Work | D45: Date | F45: The last day of work for the worker's latest termination. Includes future-dated terminations. | G45: Workday Delivered | I45: Staffing History | J45: Default Areas | K45: Last day physically worked; can be before the Termination Date.
A46: 42 | B46: 3. Key Dates & Service | C46: Retirement Date | D46: Date | F46: The effective date of worker's retirement. | G46: Workday Delivered | I46: Benefits Eligibility | J46: Benefits Eligibility | K46: Recorded retirement date.
A47: 43 | B47: 3. Key Dates & Service | C47: Length of Service - Worker | D47: Text | F47: The length of service in years, months, and days for the worker. Values for this report field will be displayed if you have access to the worker. | G47: Workday Delivered | I47: Benefits Eligibility | J47: Benefits Eligibility | K47: Text, for example '5 year(s), 3 month(s)'. Good for display, not for maths.
A48: 44 | B48: 3. Key Dates & Service | C48: Length of Service in Months | D48: Numeric | F48: The number of months of service starting on the most recent hire date for the worker. If there's a continuous service date for the worker, then the number of months is based on the continuous service date. | G48: Workday Delivered | I48: Benefits Eligibility | J48: Benefits Eligibility | K48: Numeric; use for bands, averages and calculations.
A49: 45 | B49: 3. Key Dates & Service | C49: Years of Service | D49: Numeric | F49: The years of service for the worker. | G49: Workday Delivered | I49: Employment | J49: Default Areas | K49: Numeric years of service; use for anniversary and service-award reports.
A50: 46 | B50: 3. Key Dates & Service | C50: Years in Current Job | D50: Numeric | F50: Years the candidate has been in their current job based on their most recent job application or Prospect. | G50: Workday Delivered | I50: Resume | J50: Default Areas | K50: Time in the current job profile, in years.
A51: 47 | B51: 3. Key Dates & Service | C51: Years in Current Position | D51: Numeric | F51: Returns the amount of years (to 2 decimals positions) that a worker was in their current primary position. If the worker is terminated, the current position was the last primary position the worker was in. | G51: Workday Delivered | I51: Job & Position | J51: Drill Down | K51: Time in the current position, in years.
A52: 48 | B52: 3. Key Dates & Service | C52: Next Anniversary in Years | D52: Numeric | F52: The amount of years that the worker is celebrating as their next anniversary based on their most recent hire date. | G52: Workday Delivered | I52: Employment | J52: Default Areas | K52: Upcoming service anniversary number; used for recognition reports.
A53: 49 | B53: 4. Job & Position | C53: Business Title | D53: Text | F53: The business title for the worker's primary position. If no business title is defined for a position, the position title is returned back. | G53: Workday Delivered | I53: Employment | J53: Default Areas | K53: Title shown on the profile; can differ from the job profile name.
A54: 50 | B54: 4. Job & Position | C54: Job Title | D54: Text | F54: The position title for the worker's primary position. If blank, returns the job profile title. | G54: Workday Delivered | I54: Job & Position | J54: Default Areas | K54: Job title from the position or job.
A55: 51 | B55: 4. Job & Position | C55: Job Profile | D55: Single instance | E55: Job Profile | F55: The worker job profile. | G55: Workday Delivered | I55: Job & Position | J55: Default Areas | K55: Generic job definition. Key for job architecture, compensation and EEO reporting.
A56: 52 | B56: 4. Job & Position | C56: Job Code | D56: Text | F56: The job code for the worker's primary position. | G56: Workday Delivered | I56: Job & Position | J56: Default Areas | K56: Code of the job profile; used in integrations.
A57: 53 | B57: 4. Job & Position | C57: Job Family | D57: Multi-instance | E57: Job Family | F57: The job family for the worker's primary position. | G57: Workday Delivered | I57: Job & Position | J57: Security Attribute - System User | K57: Groups related job profiles (for example Software Engineering).
A58: 54 | B58: 4. Job & Position | C58: Job Family Group | D58: Multi-instance | E58: Job Family | F58: The job family group for the worker's primary position. | G58: Workday Delivered | I58: Job & Position | J58: Security Attribute - System User | K58: Higher-level grouping of job families.
A59: 55 | B59: 4. Job & Position | C59: Job Category | D59: Single instance | E59: Job Category | F59: The job category for the worker's primary position. | G59: Workday Delivered | I59: Job & Position | J59: Security Attribute - System User | K59: Job category (tenant-configured).
A60: 56 | B60: 4. Job & Position | C60: Job Level - Primary Position | D60: Single instance | E60: Job Level | F60: Job level for the worker from the job profile associated with the worker's primary position. It is retrieved from the job profile associated with the worker's primary position. | G60: Workday Delivered | I60: Employment | J60: Security Attribute - System User | K60: Level of the job on the primary position.
A61: 57 | B61: 4. Job & Position | C61: Management Level | D61: Single instance | E61: Management Level | F61: The Management Level from the Job Profile for the worker's primary position. | G61: Workday Delivered | I61: Employment | J61: Security Attribute - System User | K61: For example Individual Contributor, Manager, Director, Executive.
A62: 58 | B62: 4. Job & Position | C62: Job Classifications - Primary Position | D62: Multi-instance | E62: Job Classification | F62: Contains the job classifications from the job profile and additional job classifications from the worker's primary position. Does not return a value if the worker has more than one position (multiple jobs). Search only. | G62: Workday Delivered | I62: Job & Position | J62: Indexed Reporting | K62: EEO-1, ISCO and other job classifications.
A63: 59 | B63: 4. Job & Position | C63: Position | D63: Single instance | E63: Position | F63: The worker's primary position. | G63: Workday Delivered | I63: Job & Position | J63: Default Areas | K63: The position (or job, in job management) the worker fills.
A64: 60 | B64: 4. Job & Position | C64: Position ID | D64: Text | F64: The unique identifier for the worker's primary position. | G64: Workday Delivered | I64: Job & Position | J64: Default Areas | K64: Position identifier; key for headcount and position control.
A65: 61 | B65: 4. Job & Position | C65: All Positions | D65: Multi-instance | E65: Position | F65: Contains all the positions a worker has held over time. This includes primary and additional jobs. | G65: Workday Delivered | I65: Staffing History | J65: Default Areas | K65: Every position the worker holds, including additional jobs.
A66: 62 | B66: 4. Job & Position | C66: Critical Job - Primary Position | D66: Boolean | F66: Returns true if the worker's primary position job is considered critical. | G66: Workday Delivered | I66: Job & Position | J66: Report Writer | K66: Flags critical jobs for succession planning.
A67: 63 | B67: 5. Organization & Management | C67: Supervisory Organization | D67: Single instance | E67: Organization | F67: The supervisory organization for the worker's primary position. | G67: Workday Delivered | I67: Organization | J67: Security Attribute - System User | K67: Main reporting structure; drives security, approvals and the org chart.
A68: 64 | B68: 5. Organization & Management | C68: Supervisory Organization - Primary Position | D68: Single instance | E68: Supervisory Organization | F68: The supervisory organization for the worker's primary position, if the supervisory organization is viewable by everyone. | G68: Workday Delivered | I68: Organization | J68: Securing Entity | K68: Supervisory org of the primary position only.
A69: 65 | B69: 5. Organization & Management | C69: Worker's Manager | D69: Multi-instance | E69: Worker | F69: The supervisory manager for the worker's primary position. | G69: Workday Delivered | I69: Employment | J69: Default Areas | K69: Manager(s) of the worker. Multi-instance, so a worker can have more than one.
A70: 66 | B70: 5. Organization & Management | C70: Manager - Level 01 | D70: Single instance | E70: Worker | F70: The immediate manager for the worker's primary position. This is the manager for the worker's supervisory organization. Example: Worker A is in Organization 1 which is managed by Worker B. This will return Worker B. | G70: Workday Delivered | I70: Organization | J70: Default Areas | K70: Top of the management chain. Use Level 01 to Level 10 to build hierarchy columns.
A71: 67 | B71: 5. Organization & Management | C71: Manager - Level 02 | D71: Single instance | E71: Worker | F71: The manager of the superior organization for the worker's primary position's supervisory organization. Example: Worker A is in Organization 1 which has a superior Organization 2. Organization 2 is managed by Worker C. This will return Worker C. | G71: Workday Delivered | I71: Organization | J71: Default Areas
A72: 68 | B72: 5. Organization & Management | C72: All Managers in Management Chain | D72: Multi-instance | E72: Worker | F72: The supervisory managers in the management chain for the worker's primary position. The user will need access to view the managers as a worker. | G72: Workday Delivered | I72: Organization | J72: Default Areas | K72: Every manager above the worker; good for 'roll-up to VP' filters.
A73: 69 | B73: 5. Organization & Management | C73: Direct Reports (Employees) | D73: Multi-instance | E73: Worker | F73: Returns all employees who are direct reports to the worker. | G73: Workday Delivered | I73: Job & Position | J73: Default Areas | K73: Employees who report directly to this worker.
A74: 70 | B74: 5. Organization & Management | C74: Number of Direct Reports | D74: Numeric | F74: The number of direct reports as of the current moment. Includes active workers, contingent workers, inactive workers, and inherited positions. | G74: Workday Delivered | I74: Job & Position | J74: Default Areas | K74: Numeric span of control.
A75: 71 | B75: 5. Organization & Management | C75: Organizations Managed | D75: Multi-instance | E75: Organization | F75: Organizations where the Workerhas been assigned to the manager role. The user must have permissions to view these organizations. Includes organizations with inherited manager roles. | G75: Workday Delivered | I75: Organization | J75: Default Areas | K75: Organizations where the worker is the manager.
A76: 72 | B76: 5. Organization & Management | C76: Cost Center | D76: Single instance | E76: Cost Center | F76: The cost center for the worker's primary position. This report field only displays 1 cost center. If the worker has more than 1 cost center, this field displays the first cost center it finds for the worker. | G76: Workday Delivered | I76: Organization | J76: Security Attribute - System User | K76: Financial cost center; key for finance reporting and payroll costing.
A77: 73 | B77: 5. Organization & Management | C77: Cost Center - ID | D77: Text | F77: The cost center id for the worker's primary position. | G77: Workday Delivered | I77: Organization | J77: Default Areas | K77: Text ID of the cost center for integrations.
A78: 74 | B78: 5. Organization & Management | C78: Cost Center - Name | D78: Text | F78: The name of the cost center for the worker's primary position. | G78: Workday Delivered | I78: Organization | J78: Default Areas
A79: 75 | B79: 5. Organization & Management | C79: Company | D79: Single instance | E79: Company | F79: The company for the worker. | G79: Workday Delivered | I79: Organization | J79: Security Attribute - System User | K79: Legal entity that employs the worker.
A80: 76 | B80: 5. Organization & Management | C80: Company - Name | D80: Text | F80: The name of the company for the worker's primary position. | G80: Workday Delivered | I80: Organization | J80: Default Areas
A81: 77 | B81: 5. Organization & Management | C81: Region | D81: Single instance | E81: Region | F81: The region for the worker's primary position. Only use this report field if the worker only has 1 region, otherwise it will pick the worker's first region it finds for them. | G81: Workday Delivered | I81: Organization | J81: Security Attribute - System User | K81: Region organization assignment.
A82: 78 | B82: 5. Organization & Management | C82: Matrix Organizations | D82: Multi-instance | E82: Matrix Organization | F82: The matrix organizations for the worker's primary position. | G82: Workday Delivered | I82: Organization | J82: Default Areas | K82: Dotted-line or matrix organizations.
A83: 79 | B83: 5. Organization & Management | C83: Business Units | D83: Multi-instance | E83: Business Unit | F83: The business units for the worker's primary job. | G83: Workday Delivered | I83: Organization | J83: Securing Entity | K83: Business unit assignments.
A84: 80 | B84: 5. Organization & Management | C84: Location | D84: Single instance | E84: Location | F84: Contains the location for the worker. | G84: Workday Delivered | I84: Organization | J84: Security Attribute - System User | K84: Work location; drives tax, holiday calendar and time zone.
A85: 81 | B85: 5. Organization & Management | C85: Location - Name | D85: Text | F85: The name of the location for the worker's primary position. | G85: Workday Delivered | I85: Organization | J85: Default Areas
A86: 82 | B86: 5. Organization & Management | C86: Location Address - City | D86: Text | F86: Location Address - City | G86: Workday Delivered | I86: Benefits Eligibility | J86: Benefits Eligibility
A87: 83 | B87: 5. Organization & Management | C87: Location Address - Country | D87: Single instance | E87: Country | F87: The country of the worker's location address. | G87: Workday Delivered | I87: Benefits Eligibility | J87: Security Attribute - System User | K87: Country of the work location. Common for global headcount.
A88: 84 | B88: 5. Organization & Management | C88: Location Hierarchy | D88: Multi-instance | E88: Location Hierarchy | F88: The location hierarchy for the location of the worker's primary position. | G88: Workday Delivered | I88: Organization | J88: Security Attribute - System User | K88: Location hierarchies the location belongs to.
A89: 85 | B89: 5. Organization & Management | C89: Pay Group | D89: Single instance | E89: Pay Group | F89: The Pay Group for the worker. | G89: Workday Delivered | I89: Payroll | J89: Security Attribute - System User | K89: Payroll pay group; determines pay schedule and run.
A90: 86 | B90: 5. Organization & Management | C90: Unions Active | D90: Multi-instance | E90: Union | F90: Contains the Unions that the Worker is currently Active in. | G90: Workday Delivered | I90: Union | J90: Security Attribute - System User | K90: Unions where the worker has an active membership.
A91: 87 | B91: 6. Contact Information | C91: Email - Primary Work | D91: Text | F91: The primary work email address for the worker. | G91: Workday Delivered | I91: Address & Phone | J91: Default Areas | K91: Primary work email. Text; ideal for exports and provisioning.
A92: 88 | B92: 6. Contact Information | C92: Email - Primary Home | D92: Text | F92: The primary home email address for the worker. | G92: Workday Delivered | I92: Address & Phone | J92: Default Areas | K92: Personal email; often used for leaver and alumni communications.
A93: 89 | B93: 6. Contact Information | C93: Phone - Primary Work | D93: Text | F93: The primary work phone number for the worker including the area code and country code. | G93: Workday Delivered | I93: Address & Phone | J93: Default Areas
A94: 90 | B94: 6. Contact Information | C94: Phone - Primary Home | D94: Text | F94: The primary home phone number for the worker including the area code and country code. | G94: Workday Delivered | I94: Address & Phone | J94: Default Areas
A95: 91 | B95: 6. Contact Information | C95: Phone Numbers | D95: Multi-instance | E95: Phone Data | F95: Contains all the phone information defined for the worker. | G95: Workday Delivered | I95: Address & Phone | J95: Default Areas | K95: All phone numbers (Phone Data objects): drill in for type, device and country code.
A96: 92 | B96: 6. Contact Information | C96: Primary Home Address | D96: Single instance | E96: Address | F96: Returns the primary Home Address instance for the worker. | G96: Workday Delivered | I96: Benefits Eligibility | J96: Benefits Eligibility | K96: Primary home address object; drill in for address components.
A97: 93 | B97: 6. Contact Information | C97: Primary Home Address - City | D97: Text | F97: The city from the primary home address of the worker | G97: Workday Delivered | I97: Benefits Eligibility | J97: Benefits Eligibility
A98: 94 | B98: 6. Contact Information | C98: Primary Home Address - State | D98: Single instance | E98: Country Region | F98: Returns the State of this Worker's Primary Home Address. | G98: Workday Delivered | I98: Benefits Eligibility | J98: Benefits Eligibility | K98: US state of the home address; key for tax and remote-work reporting.
A99: 95 | B99: 6. Contact Information | C99: Primary Home Address - Postal Code | D99: Text | F99: Returns the Postal Code of this Worker's Primary Home Address. | G99: Workday Delivered | I99: Benefits Eligibility | J99: Benefits Eligibility
A100: 96 | B100: 6. Contact Information | C100: Primary Home Address - Country | D100: Single instance | E100: Country | F100: The country from the worker's primary home address. | G100: Workday Delivered | I100: Benefits Eligibility | J100: Benefits Eligibility
A101: 97 | B101: 6. Contact Information | C101: Primary Work Address | D101: Single instance | E101: Address | F101: Returns the Primary Work Address for a Worker either defaulted from their primary job location, or from their alternate primary work address. | G101: Workday Delivered | I101: Address & Phone | J101: Default Areas | K101: Primary work address object.
...

Sheet Field Types
A1: Field Types Explained
A2: Counts are live formulas over the All Worker Fields tab.
A4: Field Type | B4: Fields | C4: % of Total | D4: What it returns | E4: How to use it in reports | F4: Common examples
A5: Text | B5: =COUNTIF('All Worker Fields'!D:D,A5) -> 600 | C5: =IFERROR(B5/SUM($B$5:$B$13),0) -> 0.18438844 | D5: A plain string value. | E5: Filter with "contains" / "equal to". Best for exports and integrations. Cannot be drilled into. | F5: Employee ID, Email - Primary Work, Business Title, Cost Center - ID
A6: Numeric | B6: =COUNTIF('All Worker Fields'!D:D,A6) -> 194 | C6: =IFERROR(B6/SUM($B$5:$B$13),0) -> 0.059618931 | D6: A number (integer or decimal). | E6: Sort, sum, average and band. Use for maths in calculated fields. | F6: FTE, Age, Years of Service, Compa-Ratio
A7: Currency | B7: =COUNTIF('All Worker Fields'!D:D,A7) -> 136 | C7: =IFERROR(B7/SUM($B$5:$B$13),0) -> 0.041794714 | D7: A monetary amount; the currency is held separately. | E7: Always show the matching Currency (and Frequency) field, or use the "Annualized in USD / Reporting Currency" variants to compare across countries. | F7: Total Base Pay - Amount, Hourly Rate - Amount
A8: Date | B8: =COUNTIF('All Worker Fields'!D:D,A8) -> 230 | C8: =IFERROR(B8/SUM($B$5:$B$13),0) -> 0.070682237 | D8: A calendar date. | E8: Filter with relative dates (for example "in the last 30 days"); use Date Difference calculated fields for tenure. | F8: Hire Date, Termination Date, Date of Birth
A9: Boolean | B9: =COUNTIF('All Worker Fields'!D:D,A9) -> 457 | C9: =IFERROR(B9/SUM($B$5:$B$13),0) -> 0.14044253 | D9: True / False. | E9: Ideal for report filters and condition logic in calculated fields and business process conditions. | F9: Is Manager, On Leave, Terminated, Exempt
A10: Single instance | B10: =COUNTIF('All Worker Fields'!D:D,A10) -> 608 | C10: =IFERROR(B10/SUM($B$5:$B$13),0) -> 0.18684696 | D10: Exactly one related business object. | E10: Shows the object's display name; drill in (or use "Lookup Related Value") to reach the object's own fields. Use as a group-by in matrix reports. | F10: Supervisory Organization, Location, Job Profile, Company
A11: Multi-instance | B11: =COUNTIF('All Worker Fields'!D:D,A11) -> 927 | C11: =IFERROR(B11/SUM($B$5:$B$13),0) -> 0.28488015 | D11: Zero or more related business objects. | E11: Use subfilters, "Extract Multi-Instance", "Count Related Instances" or a secondary business object in advanced reports. Watch for row multiplication. | F11: Worker's Manager, Employee Type, Phone Numbers, Skills
A12: Self referencing instance | B12: =COUNTIF('All Worker Fields'!D:D,A12) -> 96 | C12: =IFERROR(B12/SUM($B$5:$B$13),0) -> 0.029502151 | D12: The instance itself (or the same object type, used as a reference). | E12: Used to identify the row's own instance, for example the Worker field on the Worker object, or plan dimensions. | F12: Worker, Plan Dimension as Job Level
A13: Rich Text | B13: =COUNTIF('All Worker Fields'!D:D,A13) -> 6 | C13: =IFERROR(B13/SUM($B$5:$B$13),0) -> 0.0018438844 | D13: Formatted text (HTML). | E13: Display only; formatting may not export cleanly to Excel or integrations. | F13: Potential Assessment Value 1
A14: Total | B14: =SUM(B5:B13) -> 3254 | C14: =SUM(C5:C13) -> 1
A16: Field Source
A17: Field Source | B17: Fields | C17: % of Total | D17: Meaning
A18: Workday Delivered | B18: =COUNTIF('All Worker Fields'!C:C,A18) -> 2835 | C18: =IFERROR(B18/SUM($B$18:$B$20),0) -> 0.8712354 | D18: Delivered and maintained by Workday.
A19: Calculated | B19: =COUNTIF('All Worker Fields'!C:C,A19) -> 408 | C19: =IFERROR(B19/SUM($B$18:$B$20),0) -> 0.12538414 | D19: Tenant-built calculated field. Check its logic before reuse; it may be tenant-specific.
A20: Custom Field | B20: =COUNTIF('All Worker Fields'!C:C,A20) -> 11 | C20: =IFERROR(B20/SUM($B$18:$B$20),0) -> 0.0033804548 | D20: Tenant-defined custom object or field.

Sheet Categories
A1: Field Categories
A2: Every category in the Worker PBO with live field counts. Sorted by size.
A4: Category | B4: Total Fields | C4: Common Fields in Handbook
A5: Uncategorized | B5: =COUNTIF('All Worker Fields'!G:G,A5) -> 401 | C5: =COUNTIFS('All Worker Fields'!G:G,A5,'All Worker Fields'!I:I,"Yes") -> 1
A6: Worker Tax Elections | B6: =COUNTIF('All Worker Fields'!G:G,A6) -> 219 | C6: =COUNTIFS('All Worker Fields'!G:G,A6,'All Worker Fields'!I:I,"Yes") -> 0
A7: Benefits Eligibility | B7: =COUNTIF('All Worker Fields'!G:G,A7) -> 205 | C7: =COUNTIFS('All Worker Fields'!G:G,A7,'All Worker Fields'!I:I,"Yes") -> 39
A8: Compensation | B8: =COUNTIF('All Worker Fields'!G:G,A8) -> 205 | C8: =COUNTIFS('All Worker Fields'!G:G,A8,'All Worker Fields'!I:I,"Yes") -> 18
A9: Payroll | B9: =COUNTIF('All Worker Fields'!G:G,A9) -> 190 | C9: =COUNTIFS('All Worker Fields'!G:G,A9,'All Worker Fields'!I:I,"Yes") -> 2
A10: Organization | B10: =COUNTIF('All Worker Fields'!G:G,A10) -> 159 | C10: =COUNTIFS('All Worker Fields'!G:G,A10,'All Worker Fields'!I:I,"Yes") -> 17
A11: Address & Phone | B11: =COUNTIF('All Worker Fields'!G:G,A11) -> 113 | C11: =COUNTIFS('All Worker Fields'!G:G,A11,'All Worker Fields'!I:I,"Yes") -> 7
A12: Talent | B12: =COUNTIF('All Worker Fields'!G:G,A12) -> 107 | C12: =COUNTIFS('All Worker Fields'!G:G,A12,'All Worker Fields'!I:I,"Yes") -> 7
A13: Job & Position | B13: =COUNTIF('All Worker Fields'!G:G,A13) -> 100 | C13: =COUNTIFS('All Worker Fields'!G:G,A13,'All Worker Fields'!I:I,"Yes") -> 18
A14: Basic Bio | B14: =COUNTIF('All Worker Fields'!G:G,A14) -> 91 | C14: =COUNTIFS('All Worker Fields'!G:G,A14,'All Worker Fields'!I:I,"Yes") -> 10
A15: Recruiting | B15: =COUNTIF('All Worker Fields'!G:G,A15) -> 83 | C15: =COUNTIFS('All Worker Fields'!G:G,A15,'All Worker Fields'!I:I,"Yes") -> 2
A16: Time Off | B16: =COUNTIF('All Worker Fields'!G:G,A16) -> 82 | C16: =COUNTIFS('All Worker Fields'!G:G,A16,'All Worker Fields'!I:I,"Yes") -> 2
... A137: Year End | B137: =COUNTIF('All Worker Fields'!G:G,A137) -> 1 | C137: =COUNTIFS('All Worker Fields'!G:G,A137,'All Worker Fields'!I:I,"Yes") -> 0

Sheet Related Objects
A1: Related Business Objects (RBO)
A2: Objects reachable from Worker. "Number of Links" is from Worker_RBO.xlsx; linking fields are taken from the PBO.
A4: Related Business Object | B4: Number of Links (RBO) | C4: Single-instance Links | D4: Multi-instance Links | E4: Example Worker Fields that Return this Object
A5: Worker | B5: 88 | C5: =COUNTIFS('All Worker Fields'!E:E,A5,'All Worker Fields'!D:D,"Single instance") -> 40 | D5: =COUNTIFS('All Worker Fields'!E:E,A5,'All Worker Fields'!D:D,"Multi-instance") -> 29 | E5: All Managers in Management Chain; Direct Reports (Employees); Manager - Level 01; Manager - Level 02; Worker ...
A6: Position | B6: 47 | C6: =COUNTIFS('All Worker Fields'!E:E,A6,'All Worker Fields'!D:D,"Single instance") -> 24 | D6: =COUNTIFS('All Worker Fields'!E:E,A6,'All Worker Fields'!D:D,"Multi-instance") -> 18 | E6: All Positions; Position; Additional Jobs; Additional Jobs - All; Additional Jobs if Enabled; All Effective Positions ...
A7: Organization | B7: 35 | C7: =COUNTIFS('All Worker Fields'!E:E,A7,'All Worker Fields'!D:D,"Single instance") -> 11 | D7: =COUNTIFS('All Worker Fields'!E:E,A7,'All Worker Fields'!D:D,"Multi-instance") -> 21 | E7: Organizations Managed; Supervisory Organization; Assigned Organization; Assigned Organizations (Benefit Jobs); CF ESI Superior Orgnization; CF_ESI PC on Worker ...
A8: Location | B8: 30 | C8: =COUNTIFS('All Worker Fields'!E:E,A8,'All Worker Fields'!D:D,"Single instance") -> 18 | D8: =COUNTIFS('All Worker Fields'!E:E,A8,'All Worker Fields'!D:D,"Multi-instance") -> 11 | E8: Location; All Locations; All Locations (Benefit Jobs); All Locations (Benefits); Cost Center - Primary Locations; Headcount Plan Template Location Filters ...
A9: Currency | B9: 29 | C9: =COUNTIFS('All Worker Fields'!E:E,A9,'All Worker Fields'!D:D,"Single instance") -> 29 | D9: =COUNTIFS('All Worker Fields'!E:E,A9,'All Worker Fields'!D:D,"Multi-instance") -> 0 | E9: Total Base Pay - Currency; Benefits Annual Rate Currency; Company or Company Hierarchy Currency; Compensation Range - Currency; Competitive Market Target Benchmark - Currency; Currency for Primary Position ...
A10: Abstract Review Rating | B10: 26 | C10: =COUNTIFS('All Worker Fields'!E:E,A10,'All Worker Fields'!D:D,"Single instance") -> 22 | D10: =COUNTIFS('All Worker Fields'!E:E,A10,'All Worker Fields'!D:D,"Multi-instance") -> 4 | E10: Last Review - Overall Rating; Average Project Rating; Calibration: Column Section Rating; Calibration: Overall Performance Rating; Calibration: Row Section Rating; Calibration: Talent Based Performance Rating ...
A11: Frequency | B11: 24 | C11: =COUNTIFS('All Worker Fields'!E:E,A11,'All Worker Fields'!D:D,"Single instance") -> 24 | D11: =COUNTIFS('All Worker Fields'!E:E,A11,'All Worker Fields'!D:D,"Multi-instance") -> 0 | E11: Primary Compensation Basis - Frequency; Total Base Pay - Frequency; Compensation Range - Frequency; Frequency - Payroll; Frequency for Primary Position; Pay Frequency - Payroll ...
A12: Worker Tax Election | B12: 21 | C12: =COUNTIFS('All Worker Fields'!E:E,A12,'All Worker Fields'!D:D,"Single instance") -> 0 | D12: =COUNTIFS('All Worker Fields'!E:E,A12,'All Worker Fields'!D:D,"Multi-instance") -> 21 | E12: All Local County Withholding (Resident); All Local County Withholding (Work); All State Withholding Elections; Erroneously Has Exempt Reason or Domicile State; Erroneously Has MSRR Exempt or Exempt; Erroneously Has Spouse Indicator, Marital Status, or Reciprocity Tax Credit ...
A13: Address | B13: 20 | C13: =COUNTIFS('All Worker Fields'!E:E,A13,'All Worker Fields'!D:D,"Single instance") -> 8 | D13: =COUNTIFS('All Worker Fields'!E:E,A13,'All Worker Fields'!D:D,"Multi-instance") -> 11 | E13: Primary Home Address; Primary Work Address; Addresses; Addresses - Local; Addresses without Default Work Address; All Home Addresses ...
A14: Personal Information Configurable Field Country Agnostic | B14: 18 | C14: =COUNTIFS('All Worker Fields'!E:E,A14,'All Worker Fields'!D:D,"Single instance") -> 0 | D14: =COUNTIFS('All Worker Fields'!E:E,A14,'All Worker Fields'!D:D,"Multi-instance") -> 18 | E14: Non Country Specific Section 1 - Field 1; Non Country Specific Section 1 - Field 1 (Locale Sensitive); Non Country Specific Section 1 - Field 2; Non Country Specific Section 1 - Field 2 (Locale Sensitive); Non Country Specific Section 1 - Field 3; Non Country Specific Section 1 - Field 3 (Locale Sensitive) ...
A15: Personal Information Configurable Field for Country | B15: 18 | C15: =COUNTIFS('All Worker Fields'!E:E,A15,'All Worker Fields'!D:D,"Single instance") -> 0 | D15: =COUNTIFS('All Worker Fields'!E:E,A15,'All Worker Fields'!D:D,"Multi-instance") -> 18 | E15: Country Specific Section 1 - Field 1; Country Specific Section 1 - Field 1 (Locale Sensitive); Country Specific Section 1 - Field 2; Country Specific Section 1 - Field 2 (Locale Sensitive); Country Specific Section 1 - Field 3; Country Specific Section 1 - Field 3 (Locale Sensitive) ...
A16: Union | B16: 18 | C16: =COUNTIFS('All Worker Fields'!E:E,A16,'All Worker Fields'!D:D,"Single instance") -> 0 | D16: =COUNTIFS('All Worker Fields'!E:E,A16,'All Worker Fields'!D:D,"Multi-instance") -> 18 | E16: Unions Active; Active Dues Paying Unions as of Period Start Date; Active Dues Paying Unions as of Sub Period End Date; Active Unions as of Leave Start Date; Active Unions as of Period End Date; Active Unions as of Period Start Date ...
... A84: Benefit Change | B84: 4 | C84: =COUNTIFS('All Worker Fields'!E:E,A84,'All Worker Fields'!D:D,"Single instance") -> 0 | D84: =COUNTIFS('All Worker Fields'!E:E,A84,'All Worker Fields'!D:D,"Multi-instance") -> 4 | E84: Benefit Changes; Benefit Changes by Plan; Insurance Election Changes; RPT EMI Worker Benefit Changes within prompts
A85: Communication Method Usage | B85: 4 | C85: =COUNTIFS('All Worker Fields'!E:E,A85,'All Worker Fields'!D:D,"Single instance") -> 0 | D85: =COUNTIFS('All Worker Fields'!E:E,A85,'All Worker Fields'!D:D,"Multi-instance") -> 0
A86: Compensation Grade | B86: 4 | C86: =COUNTIFS('All Worker Fields'!E:E,A86,'All Worker Fields'!D:D,"Single instance") -> 2 | D86: =COUNTIFS('All Worker Fields'!E:E,A86,'All Worker Fields'!D:D,"Multi-instance") -> 1 | E86: Compensation Grade; Compensation Grades (Benefit Jobs); Plan Dimension as Compensation Grade; Retained Compensation Grade
A87: Country and Nationality | B87: 4 | C87: =COUNTIFS('All Worker Fields'!E:E,A87,'All Worker Fields'!D:D,"Single instance") -> 1 | D87: =COUNTIFS('All Worker Fields'!E:E,A87,'All Worker Fields'!D:D,"Multi-instance") -> 3 | E87: Primary Nationality (Worker) - Locale Sensitive; Additional Nationalities (Worker); Additional Nationalities (Worker) - Locale Sensitive; All Nationalities (Worker)
A88: Disability | B88: 4 | C88: =COUNTIFS('All Worker Fields'!E:E,A88,'All Worker Fields'!D:D,"Single instance") -> 0 | D88: =COUNTIFS('All Worker Fields'!E:E,A88,'All Worker Fields'!D:D,"Multi-instance") -> 4 | E88: Disability (Locale Sensitive and Country Securable); Disability (Locale Sensitive); Disability - Active and Inactive (Locale Sensitive and Country Securable); Disability - Active and Inactive (Locale Sensitive)
A89: External Pay Group (Do Not Use) | B89: 4 | C89: =COUNTIFS('All Worker Fields'!E:E,A89,'All Worker Fields'!D:D,"Single instance") -> 3 | D89: =COUNTIFS('All Worker Fields'!E:E,A89,'All Worker Fields'!D:D,"Multi-instance") -> 1 | E89: External Pay Group; External Pay Group as of Period End Date; External Pay Group as of Period Start Date; External Pay Groups (Benefit Jobs)
A90: External Payroll Actual | B90: 4 | C90: =COUNTIFS('All Worker Fields'!E:E,A90,'All Worker Fields'!D:D,"Single instance") -> 0 | D90: =COUNTIFS('All Worker Fields'!E:E,A90,'All Worker Fields'!D:D,"Multi-instance") -> 4 | E90: External Payroll Actuals (All for Primary Job); External Payroll Actuals (All for Worker); External Payroll Actuals (Completed for Primary Job); External Payroll Actuals (Completed for Worker)
A91: Feedback Given | B91: 4 | C91: =COUNTIFS('All Worker Fields'!E:E,A91,'All Worker Fields'!D:D,"Single instance") -> 0 | D91: =COUNTIFS('All Worker Fields'!E:E,A91,'All Worker Fields'!D:D,"Multi-instance") -> 3 | E91: Feedback Given; Feedback Received; Feedback Received - Anytime
A92: Flex Team Opening | B92: 4 | C92: =COUNTIFS('All Worker Fields'!E:E,A92,'All Worker Fields'!D:D,"Single instance") -> 0 | D92: =COUNTIFS('All Worker Fields'!E:E,A92,'All Worker Fields'!D:D,"Multi-instance") -> 4 | E92: Active Flex Teams; Completed Flex Teams; Flex Teams; Interested Flex Teams
A93: Former Worker | B93: 4 | C93: =COUNTIFS('All Worker Fields'!E:E,A93,'All Worker Fields'!D:D,"Single instance") -> 3 | D93: =COUNTIFS('All Worker Fields'!E:E,A93,'All Worker Fields'!D:D,"Multi-instance") -> 0 | E93: Former Worker; Linked Prior Worker (Former); Merged Former Worker
A94: Hukou Type | B94: 4 | C94: =COUNTIFS('All Worker Fields'!E:E,A94,'All Worker Fields'!D:D,"Single instance") -> 4 | D94: =COUNTIFS('All Worker Fields'!E:E,A94,'All Worker Fields'!D:D,"Multi-instance") -> 0 | E94: Hukou Type; Hukou Type (Country Securable); Hukou Type as of Period End Date; Hukou Type as of Period Start Date
A95: Internet Email Address | B95: 4 | C95: =COUNTIFS('All Worker Fields'!E:E,A95,'All Worker Fields'!D:D,"Single instance") -> 0 | D95: =COUNTIFS('All Worker Fields'!E:E,A95,'All Worker Fields'!D:D,"Multi-instance") -> 4 | E95: Email - Home; Email - Work; Emails; Public Email Addresses
A96: Leave Type | B96: 4 | C96: =COUNTIFS('All Worker Fields'!E:E,A96,'All Worker Fields'!D:D,"Single instance") -> 0 | D96: =COUNTIFS('All Worker Fields'!E:E,A96,'All Worker Fields'!D:D,"Multi-instance") -> 4 | E96: Leave Type; Active Leave Types that Track Balance; All Eligible Leave Types for Worker; Leave Types for Worker
A97: Location Hierarchy | B97: 4 | C97: =COUNTIFS('All Worker Fields'!E:E,A97,'All Worker Fields'!D:D,"Single instance") -> 0 | D97: =COUNTIFS('All Worker Fields'!E:E,A97,'All Worker Fields'!D:D,"Multi-instance") -> 3 | E97: Location Hierarchy; Location Hierarchy for Worker as of Period End Date; Location Hierarchy for Worker as of Period Start Date; Plan Dimension as Location Hierarchy
... A144: Personal Information for Country | B144: 3 | C144: =COUNTIFS('All Worker Fields'!E:E,A144,'All Worker Fields'!D:D,"Single instance") -> 2 | D144: =COUNTIFS('All Worker Fields'!E:E,A144,'All Worker Fields'!D:D,"Multi-instance") -> 1 | E144: All Personal Information for Country; Personal Information for Country; Personal Information for Country of Primary Position
A145: Phone Interface | B145: 3 | C145: =COUNTIFS('All Worker Fields'!E:E,A145,'All Worker Fields'!D:D,"Single instance") -> 0 | D145: =COUNTIFS('All Worker Fields'!E:E,A145,'All Worker Fields'!D:D,"Multi-instance") -> 0
A146: Project | B146: 3 | C146: =COUNTIFS('All Worker Fields'!E:E,A146,'All Worker Fields'!D:D,"Single instance") -> 0 | D146: =COUNTIFS('All Worker Fields'!E:E,A146,'All Worker Fields'!D:D,"Multi-instance") -> 2 | E146: Plan Dimension as Project; Worker Projects - Directly Assigned; Worker Projects - Do Not Use
A147: Project Resource Plan Detail | B147: 3 | C147: =COUNTIFS('All Worker Fields'!E:E,A147,'All Worker Fields'!D:D,"Single instance") -> 0 | D147: =COUNTIFS('All Worker Fields'!E:E,A147,'All Worker Fields'!D:D,"Multi-instance") -> 3 | E147: Assigned Resource Plan Details for Worker within Date Range; Resource Plan Details; Resource Plan Lines with Pending Request
A148: Project Role | B148: 3 | C148: =COUNTIFS('All Worker Fields'!E:E,A148,'All Worker Fields'!D:D,"Single instance") -> 0 | D148: =COUNTIFS('All Worker Fields'!E:E,A148,'All Worker Fields'!D:D,"Multi-instance") -> 2 | E148: Plan Dimension as Project Role; Project Roles; Project Roles for Worker's Time
A149: Pronoun | B149: 3 | C149: =COUNTIFS('All Worker Fields'!E:E,A149,'All Worker Fields'!D:D,"Single instance") -> 1 | D149: =COUNTIFS('All Worker Fields'!E:E,A149,'All Worker Fields'!D:D,"Multi-instance") -> 1 | E149: Pronoun (Locale Sensitive); Pronouns (Locale Sensitive)
A150: Rank | B150: 3 | C150: =COUNTIFS('All Worker Fields'!E:E,A150,'All Worker Fields'!D:D,"Single instance") -> 1 | D150: =COUNTIFS('All Worker Fields'!E:E,A150,'All Worker Fields'!D:D,"Multi-instance") -> 2 | E150: Academic Rank for Committee Candidate; Academic Rank for Primary Academic Appointment; Academic Ranks
A151: Scheduling Organization | B151: 3 | C151: =COUNTIFS('All Worker Fields'!E:E,A151,'All Worker Fields'!D:D,"Single instance") -> 2 | D151: =COUNTIFS('All Worker Fields'!E:E,A151,'All Worker Fields'!D:D,"Multi-instance") -> 1 | E151: All Scheduling Organizations for Worker; Primary High Level Scheduling Organization; Primary Scheduling Organization
A152: Sexual Orientation | B152: 3 | C152: =COUNTIFS('All Worker Fields'!E:E,A152,'All Worker Fields'!D:D,"Single instance") -> 1 | D152: =COUNTIFS('All Worker Fields'!E:E,A152,'All Worker Fields'!D:D,"Multi-instance") -> 1 | E152: Sexual Orientation (Locale Sensitive); Sexual Orientations (Locale Sensitive)
A153: Skill Detail | B153: 3 | C153: =COUNTIFS('All Worker Fields'!E:E,A153,'All Worker Fields'!D:D,"Single instance") -> 0 | D153: =COUNTIFS('All Worker Fields'!E:E,A153,'All Worker Fields'!D:D,"Multi-instance") -> 3 | E153: All Mentor Skills; Skill for Worker; Suggested Skills
A154: Skill Item Promptable | B154: 3 | C154: =COUNTIFS('All Worker Fields'!E:E,A154,'All Worker Fields'!D:D,"Single instance") -> 0 | D154: =COUNTIFS('All Worker Fields'!E:E,A154,'All Worker Fields'!D:D,"Multi-instance") -> 3 | E154: All Candidate Skills; All Skills; Skill Interests
A155: Social Network Account | B155: 3 | C155: =COUNTIFS('All Worker Fields'!E:E,A155,'All Worker Fields'!D:D,"Single instance") -> 0 | D155: =COUNTIFS('All Worker Fields'!E:E,A155,'All Worker Fields'!D:D,"Multi-instance") -> 2 | E155: Social; Social Network Accounts
A156: Staffing Event | B156: 3 | C156: =COUNTIFS('All Worker Fields'!E:E,A156,'All Worker Fields'!D:D,"Single instance") -> 0 | D156: =COUNTIFS('All Worker Fields'!E:E,A156,'All Worker Fields'!D:D,"Multi-instance") -> 3 | E156: Staffing History - All; Staffing History - Approved; Staffing History Approved for Business Rules
A157: State Exempt Reason | B157: 3 | C157: =COUNTIFS('All Worker Fields'!E:E,A157,'All Worker Fields'!D:D,"Single instance") -> 0 | D157: =COUNTIFS('All Worker Fields'!E:E,A157,'All Worker Fields'!D:D,"Multi-instance") -> 3 | E157: State Withholding (Domicile) - Exempt Reason; State Withholding (Resident) - Exempt Reason; State Withholding (Work) - Exempt Reason
... A203: Delegation | B203: 2 | C203: =COUNTIFS('All Worker Fields'!E:E,A203,'All Worker Fields'!D:D,"Single instance") -> 0 | D203: =COUNTIFS('All Worker Fields'!E:E,A203,'All Worker Fields'!D:D,"Multi-instance") -> 2 | E203: Current Delegations; Delegation Assignments
A204: Diagramming Node Proxy | B204: 2 | C204: =COUNTIFS('All Worker Fields'!E:E,A204,'All Worker Fields'!D:D,"Single instance") -> 0 | D204: =COUNTIFS('All Worker Fields'!E:E,A204,'All Worker Fields'!D:D,"Multi-instance") -> 0
A205: Disability Status | B205: 2 | C205: =COUNTIFS('All Worker Fields'!E:E,A205,'All Worker Fields'!D:D,"Single instance") -> 0 | D205: =COUNTIFS('All Worker Fields'!E:E,A205,'All Worker Fields'!D:D,"Multi-instance") -> 2 | E205: Disability Statuses; Disability Statuses (Country Securable)
A206: Email Interface | B206: 2 | C206: =COUNTIFS('All Worker Fields'!E:E,A206,'All Worker Fields'!D:D,"Single instance") -> 0 | D206: =COUNTIFS('All Worker Fields'!E:E,A206,'All Worker Fields'!D:D,"Multi-instance") -> 0
A207: Emergency Contact | B207: 2 | C207: =COUNTIFS('All Worker Fields'!E:E,A207,'All Worker Fields'!D:D,"Single instance") -> 0 | D207: =COUNTIFS('All Worker Fields'!E:E,A207,'All Worker Fields'!D:D,"Multi-instance") -> 2 | E207: Emergency Contacts; Emergency Contacts to Recover from 5/8/2015-5/16/2015
A208: Employee Probation Period | B208: 2 | C208: =COUNTIFS('All Worker Fields'!E:E,A208,'All Worker Fields'!D:D,"Single instance") -> 1 | D208: =COUNTIFS('All Worker Fields'!E:E,A208,'All Worker Fields'!D:D,"Multi-instance") -> 1 | E208: Probation Period; Probation Periods
A209: Employee Probation Period Type | B209: 2 | C209: =COUNTIFS('All Worker Fields'!E:E,A209,'All Worker Fields'!D:D,"Single instance") -> 2 | D209: =COUNTIFS('All Worker Fields'!E:E,A209,'All Worker Fields'!D:D,"Multi-instance") -> 0 | E209: Probation Type; Probation Type (Not Effective Dated)
A210: Employment ID | B210: 2 | C210: =COUNTIFS('All Worker Fields'!E:E,A210,'All Worker Fields'!D:D,"Single instance") -> 1 | D210: =COUNTIFS('All Worker Fields'!E:E,A210,'All Worker Fields'!D:D,"Multi-instance") -> 1 | E210: Worker IRL Effective Primary Employment ID; Worker IRL Employment IDs
A211: Establishment | B211: 2 | C211: =COUNTIFS('All Worker Fields'!E:E,A211,'All Worker Fields'!D:D,"Single instance") -> 2 | D211: =COUNTIFS('All Worker Fields'!E:E,A211,'All Worker Fields'!D:D,"Multi-instance") -> 0 | E211: Establishment; Worker's Establishment (Benefits)
A212: Evaluation Event | B212: 2 | C212: =COUNTIFS('All Worker Fields'!E:E,A212,'All Worker Fields'!D:D,"Single instance") -> 0 | D212: =COUNTIFS('All Worker Fields'!E:E,A212,'All Worker Fields'!D:D,"Multi-instance") -> 2 | E212: Evaluations - All Completed; Evaluations - All Statuses
A213: Exempt Reason | B213: 2 | C213: =COUNTIFS('All Worker Fields'!E:E,A213,'All Worker Fields'!D:D,"Single instance") -> 0 | D213: =COUNTIFS('All Worker Fields'!E:E,A213,'All Worker Fields'!D:D,"Multi-instance") -> 2 | E213: Federal Withholding: FICA - Medicare Exempt Reasons; Federal Withholding: FICA - OASDI Exempt Reasons
A214: External Disability Self-Identification Record | B214: 2 | C214: =COUNTIFS('All Worker Fields'!E:E,A214,'All Worker Fields'!D:D,"Single instance") -> 1 | D214: =COUNTIFS('All Worker Fields'!E:E,A214,'All Worker Fields'!D:D,"Multi-instance") -> 1 | E214: External Disability All Records; Latest External Disability Response Record
A215: External or Internal Candidate | B215: 2 | C215: =COUNTIFS('All Worker Fields'!E:E,A215,'All Worker Fields'!D:D,"Single instance") -> 0 | D215: =COUNTIFS('All Worker Fields'!E:E,A215,'All Worker Fields'!D:D,"Multi-instance") -> 0 | E215: Candidate; External Candidate for Business Process
A216: External US Federal Disability Self-Identification Record | B216: 2 | C216: =COUNTIFS('All Worker Fields'!E:E,A216,'All Worker Fields'!D:D,"Single instance") -> 1 | D216: =COUNTIFS('All Worker Fields'!E:E,A216,'All Worker Fields'!D:D,"Multi-instance") -> 1 | E216: External Disability (SF-256) All Records; Latest External Disability Response Record (SF-256)
A217: External US Federal Ethnicity and Race Self-Identification Record | B217: 2 | C217: =COUNTIFS('All Worker Fields'!E:E,A217,'All Worker Fields'!D:D,"Single instance") -> 1 | D217: =COUNTIFS('All Worker Fields'!E:E,A217,'All Worker Fields'!D:D,"Multi-instance") -> 1 | E217: External Ethnicity & Race (SF-181) All Records; Latest External Ethnicity & Race Response Record (SF-181)
A218: FTE Dimension (Abstract) | B218: 2 | C218: =COUNTIFS('All Worker Fields'!E:E,A218,'All Worker Fields'!D:D,"Single instance") -> 2 | D218: =COUNTIFS('All Worker Fields'!E:E,A218,'All Worker Fields'!D:D,"Multi-instance") -> 0 | E218: FTE Dimension: Total Blended FTE; FTE Dimension: Total FTE
... A223: Hire Event | B223: 2 | C223: =COUNTIFS('All Worker Fields'!E:E,A223,'All Worker Fields'!D:D,"Single instance") -> 0 | D223: =COUNTIFS('All Worker Fields'!E:E,A223,'All Worker Fields'!D:D,"Multi-instance") -> 1 | E223: Hire History - Approved
A224: Instant Messenger Account Interface | B224: 2 | C224: =COUNTIFS('All Worker Fields'!E:E,A224,'All Worker Fields'!D:D,"Single instance") -> 0 | D224: =COUNTIFS('All Worker Fields'!E:E,A224,'All Worker Fields'!D:D,"Multi-instance") -> 0
A225: Integration Identifier | B225: 2 | C225: =COUNTIFS('All Worker Fields'!E:E,A225,'All Worker Fields'!D:D,"Single instance") -> 0 | D225: =COUNTIFS('All Worker Fields'!E:E,A225,'All Worker Fields'!D:D,"Multi-instance") -> 2 | E225: Integration Identifier; Location - Integration Identifiers
A226: Internal Compensation Benchmark for Worker | B226: 2 | C226: =COUNTIFS('All Worker Fields'!E:E,A226,'All Worker Fields'!D:D,"Single instance") -> 2 | D226: =COUNTIFS('All Worker Fields'!E:E,A226,'All Worker Fields'!D:D,"Multi-instance") -> 0 | E226: Internal Compensation Benchmark for Worker; Internal Primary Compensation Basis Benchmark for Worker
A227: Job Category | B227: 2 | C227: =COUNTIFS('All Worker Fields'!E:E,A227,'All Worker Fields'!D:D,"Single instance") -> 1 | D227: =COUNTIFS('All Worker Fields'!E:E,A227,'All Worker Fields'!D:D,"Multi-instance") -> 0 | E227: Job Category; Plan Dimension as Job Category
A228: Job History | B228: 2 | C228: =COUNTIFS('All Worker Fields'!E:E,A228,'All Worker Fields'!D:D,"Single instance") -> 0 | D228: =COUNTIFS('All Worker Fields'!E:E,A228,'All Worker Fields'!D:D,"Multi-instance") -> 2 | E228: Job History - Skills and Experience; Job History Displayed With Company Name
A229: Job Level | B229: 2 | C229: =COUNTIFS('All Worker Fields'!E:E,A229,'All Worker Fields'!D:D,"Single instance") -> 1 | D229: =COUNTIFS('All Worker Fields'!E:E,A229,'All Worker Fields'!D:D,"Multi-instance") -> 0 | E229: Job Level - Primary Position; Plan Dimension as Job Level
A230: Learning Enrollment | B230: 2 | C230: =COUNTIFS('All Worker Fields'!E:E,A230,'All Worker Fields'!D:D,"Single instance") -> 0 | D230: =COUNTIFS('All Worker Fields'!E:E,A230,'All Worker Fields'!D:D,"Multi-instance") -> 2 | E230: Latest Learning Enrollments; Learning Enrollments
A231: Leave Request Event | B231: 2 | C231: =COUNTIFS('All Worker Fields'!E:E,A231,'All Worker Fields'!D:D,"Single instance") -> 1 | D231: =COUNTIFS('All Worker Fields'!E:E,A231,'All Worker Fields'!D:D,"Multi-instance") -> 1 | E231: Leave of Absence Requests; CF ESI Leave of Absence Latest
A232: LGBT Identification | B232: 2 | C232: =COUNTIFS('All Worker Fields'!E:E,A232,'All Worker Fields'!D:D,"Single instance") -> 0 | D232: =COUNTIFS('All Worker Fields'!E:E,A232,'All Worker Fields'!D:D,"Multi-instance") -> 2 | E232: Sexual Orientation & Gender Identity; Sexual Orientation & Gender Identity (Country Securable)
A233: LinkedIn Person | B233: 2 | C233: =COUNTIFS('All Worker Fields'!E:E,A233,'All Worker Fields'!D:D,"Single instance") -> 1 | D233: =COUNTIFS('All Worker Fields'!E:E,A233,'All Worker Fields'!D:D,"Multi-instance") -> 1 | E233: LinkedIn Recruiter System Connect - First Exported By; LinkedIn Recruiter System Connect - Recruiter Seats Who Exported
A234: Loss Impact | B234: 2 | C234: =COUNTIFS('All Worker Fields'!E:E,A234,'All Worker Fields'!D:D,"Single instance") -> 2 | D234: =COUNTIFS('All Worker Fields'!E:E,A234,'All Worker Fields'!D:D,"Multi-instance") -> 0 | E234: Loss Impact; Assess Potential Loss Impact
A235: Manager Snapshot Interface | B235: 2 | C235: =COUNTIFS('All Worker Fields'!E:E,A235,'All Worker Fields'!D:D,"Single instance") -> 0 | D235: =COUNTIFS('All Worker Fields'!E:E,A235,'All Worker Fields'!D:D,"Multi-instance") -> 2 | E235: Manager Change; Manager Change as of Effective Date
A236: Marital Status | B236: 2 | C236: =COUNTIFS('All Worker Fields'!E:E,A236,'All Worker Fields'!D:D,"Single instance") -> 2 | D236: =COUNTIFS('All Worker Fields'!E:E,A236,'All Worker Fields'!D:D,"Multi-instance") -> 0 | E236: Marital Status; Marital Status (Country Securable)
... A270: Scheduling Worker Preferences Snapshot | B270: 2 | C270: =COUNTIFS('All Worker Fields'!E:E,A270,'All Worker Fields'!D:D,"Single instance") -> 1 | D270: =COUNTIFS('All Worker Fields'!E:E,A270,'All Worker Fields'!D:D,"Multi-instance") -> 0 | E270: Scheduling Worker Preferences
A271: Securing Entity | B271: 2 | C271: =COUNTIFS('All Worker Fields'!E:E,A271,'All Worker Fields'!D:D,"Single instance") -> 0 | D271: =COUNTIFS('All Worker Fields'!E:E,A271,'All Worker Fields'!D:D,"Multi-instance") -> 0
A272: Self-Identification of Disability Status | B272: 2 | C272: =COUNTIFS('All Worker Fields'!E:E,A272,'All Worker Fields'!D:D,"Single instance") -> 2 | D272: =COUNTIFS('All Worker Fields'!E:E,A272,'All Worker Fields'!D:D,"Multi-instance") -> 0 | E272: Latest External Disability Status; Self-Identification of Disability Status
A273: Self-Identification of Racial Category (SF-181) | B273: 2 | C273: =COUNTIFS('All Worker Fields'!E:E,A273,'All Worker Fields'!D:D,"Single instance") -> 0 | D273: =COUNTIFS('All Worker Fields'!E:E,A273,'All Worker Fields'!D:D,"Multi-instance") -> 2 | E273: Latest External Racial Category Response (SF-181); Self-Identification of Racial Category (SF-181)
A274: Skill Rating | B274: 2 | C274: =COUNTIFS('All Worker Fields'!E:E,A274,'All Worker Fields'!D:D,"Single instance") -> 0 | D274: =COUNTIFS('All Worker Fields'!E:E,A274,'All Worker Fields'!D:D,"Multi-instance") -> 2 | E274: Self-Ratings from In Progress Skill Assessment; Skill Ratings for Worker
A275: Stock Grant | B275: 2 | C275: =COUNTIFS('All Worker Fields'!E:E,A275,'All Worker Fields'!D:D,"Single instance") -> 0 | D275: =COUNTIFS('All Worker Fields'!E:E,A275,'All Worker Fields'!D:D,"Multi-instance") -> 2 | E275: Stock Grants; Stock Grants - All Statuses
A276: Supplier | B276: 2 | C276: =COUNTIFS('All Worker Fields'!E:E,A276,'All Worker Fields'!D:D,"Single instance") -> 1 | D276: =COUNTIFS('All Worker Fields'!E:E,A276,'All Worker Fields'!D:D,"Multi-instance") -> 0 | E276: Contingent Worker Supplier; Plan Dimension as Supplier
A277: Talent Highlight | B277: 2 | C277: =COUNTIFS('All Worker Fields'!E:E,A277,'All Worker Fields'!D:D,"Single instance") -> 0 | D277: =COUNTIFS('All Worker Fields'!E:E,A277,'All Worker Fields'!D:D,"Multi-instance") -> 2 | E277: Managed Talent Highlights; Talent Highlights
A278: Termination Event | B278: 2 | C278: =COUNTIFS('All Worker Fields'!E:E,A278,'All Worker Fields'!D:D,"Single instance") -> 1 | D278: =COUNTIFS('All Worker Fields'!E:E,A278,'All Worker Fields'!D:D,"Multi-instance") -> 1 | E278: Termination History - Approved; Last Termination Event
A279: Time Accumulator Threshold Rule Opt Out Event | B279: 2 | C279: =COUNTIFS('All Worker Fields'!E:E,A279,'All Worker Fields'!D:D,"Single instance") -> 0 | D279: =COUNTIFS('All Worker Fields'!E:E,A279,'All Worker Fields'!D:D,"Multi-instance") -> 2 | E279: Time Accumulator Threshold Rule Opt Outs for Worker; Worker's Time Accumulator Threshold Rules Opt-Out Events
A280: Time Clock Event | B280: 2 | C280: =COUNTIFS('All Worker Fields'!E:E,A280,'All Worker Fields'!D:D,"Single instance") -> 0 | D280: =COUNTIFS('All Worker Fields'!E:E,A280,'All Worker Fields'!D:D,"Multi-instance") -> 2 | E280: Recent Time Clock Events; Time Clock Events for Date Range
A281: Time Entry Code | B281: 2 | C281: =COUNTIFS('All Worker Fields'!E:E,A281,'All Worker Fields'!D:D,"Single instance") -> 0 | D281: =COUNTIFS('All Worker Fields'!E:E,A281,'All Worker Fields'!D:D,"Multi-instance") -> 0
A282: Time Zone | B282: 2 | C282: =COUNTIFS('All Worker Fields'!E:E,A282,'All Worker Fields'!D:D,"Single instance") -> 0 | D282: =COUNTIFS('All Worker Fields'!E:E,A282,'All Worker Fields'!D:D,"Multi-instance") -> 1 | E282: Time Zone of Location of Worker's Primary Position
A283: Timesheet | B283: 2 | C283: =COUNTIFS('All Worker Fields'!E:E,A283,'All Worker Fields'!D:D,"Single instance") -> 0 | D283: =COUNTIFS('All Worker Fields'!E:E,A283,'All Worker Fields'!D:D,"Multi-instance") -> 2 | E283: Project Timesheets - All Statuses; Project Timesheets - All Statuses for Date parms
A284: Track Type Category | B284: 2 | C284: =COUNTIFS('All Worker Fields'!E:E,A284,'All Worker Fields'!D:D,"Single instance") -> 1 | D284: =COUNTIFS('All Worker Fields'!E:E,A284,'All Worker Fields'!D:D,"Multi-instance") -> 1 | E284: Academic Track Type Categories; Academic Track Type Category for Primary Academic Appointment
A285: Trended Record Type | B285: 2 | C285: =COUNTIFS('All Worker Fields'!E:E,A285,'All Worker Fields'!D:D,"Single instance") -> 2 | D285: =COUNTIFS('All Worker Fields'!E:E,A285,'All Worker Fields'!D:D,"Multi-instance") -> 0 | E285: Activity; Snapshot
A286: Uniform Service Reserve Status | B286: 2 | C286: =COUNTIFS('All Worker Fields'!E:E,A286,'All Worker Fields'!D:D,"Single instance") -> 2 | D286: =COUNTIFS('All Worker Fields'!E:E,A286,'All Worker Fields'!D:D,"Multi-instance") -> 0 | E286: Uniform Service Reserve Status; Uniform Service Reserve Status (Locale Sensitive)
A287: Vaccination | B287: 2 | C287: =COUNTIFS('All Worker Fields'!E:E,A287,'All Worker Fields'!D:D,"Single instance") -> 1 | D287: =COUNTIFS('All Worker Fields'!E:E,A287,'All Worker Fields'!D:D,"Multi-instance") -> 1 | E287: Latest Vaccination; Vaccinations
A288: Veterans Preference | B288: 2 | C288: =COUNTIFS('All Worker Fields'!E:E,A288,'All Worker Fields'!D:D,"Single instance") -> 0 | D288: =COUNTIFS('All Worker Fields'!E:E,A288,'All Worker Fields'!D:D,"Multi-instance") -> 2 | E288: Veteran's Preference; Veteran's Preference (Locale Sensitive)
A289: Web Address Interface | B289: 2 | C289: =COUNTIFS('All Worker Fields'!E:E,A289,'All Worker Fields'!D:D,"Single instance") -> 0 | D289: =COUNTIFS('All Worker Fields'!E:E,A289,'All Worker Fields'!D:D,"Multi-instance") -> 0
A290: Withholding Order | B290: 2 | C290: =COUNTIFS('All Worker Fields'!E:E,A290,'All Worker Fields'!D:D,"Single instance") -> 0 | D290: =COUNTIFS('All Worker Fields'!E:E,A290,'All Worker Fields'!D:D,"Multi-instance") -> 2 | E290: Withholding Orders (Active); Withholding Orders (All)
A291: Worker Calibration Event | B291: 2 | C291: =COUNTIFS('All Worker Fields'!E:E,A291,'All Worker Fields'!D:D,"Single instance") -> 1 | D291: =COUNTIFS('All Worker Fields'!E:E,A291,'All Worker Fields'!D:D,"Multi-instance") -> 1 | E291: Worker Calibration Event In Progress; Worker Calibration Events
A292: Worker Common Facet Derived | B292: 2 | C292: =COUNTIFS('All Worker Fields'!E:E,A292,'All Worker Fields'!D:D,"Single instance") -> 0 | D292: =COUNTIFS('All Worker Fields'!E:E,A292,'All Worker Fields'!D:D,"Multi-instance") -> 0
A293: Worker Document | B293: 2 | C293: =COUNTIFS('All Worker Fields'!E:E,A293,'All Worker Fields'!D:D,"Single instance") -> 0 | D293: =COUNTIFS('All Worker Fields'!E:E,A293,'All Worker Fields'!D:D,"Multi-instance") -> 2 | E293: Education Attachments; Worker Documents
A294: Worker Talent Review Event | B294: 2 | C294: =COUNTIFS('All Worker Fields'!E:E,A294,'All Worker Fields'!D:D,"Single instance") -> 1 | D294: =COUNTIFS('All Worker Fields'!E:E,A294,'All Worker Fields'!D:D,"Multi-instance") -> 1 | E294: All Talent Review Events; Talent Review Event
A295: Workplace Test | B295: 2 | C295: =COUNTIFS('All Worker Fields'!E:E,A295,'All Worker Fields'!D:D,"Single instance") -> 1 | D295: =COUNTIFS('All Worker Fields'!E:E,A295,'All Worker Fields'!D:D,"Multi-instance") -> 1 | E295: Latest Workplace Test; Workplace Tests
A296: Aboriginal/Indigenous Identification Details | B296: 1 | C296: =COUNTIFS('All Worker Fields'!E:E,A296,'All Worker Fields'!D:D,"Single instance") -> 0 | D296: =COUNTIFS('All Worker Fields'!E:E,A296,'All Worker Fields'!D:D,"Multi-instance") -> 1 | E296: Aboriginal/Indigenous Identification Details
...

Sheet All Worker Fields
A1: Field Name | B1: Description | C1: Field Source | D1: Field Type | E1: Related Business Object | F1: Built-in Prompts | G1: Category | H1: Authorized Usage | I1: Common?
A2: (Active) Relocation - Long Term Areas | B2: The active relocation areas that the employee is willing to relocate to in the long term. | C2: Workday Delivered | D2: Multi-instance | E2: Relocation Area | G2: Career Development | H2: Default Areas
A3: (Active) Relocation - Short Term Areas | B3: The active relocation areas that the employee is willing to relocate to in the short term. | C3: Workday Delivered | D3: Multi-instance | E3: Relocation Area | G3: Career Development | H3: Default Areas
A4: Aboriginal/Indigenous Identification | B4: A person's response to whether or not they identify as aboriginal/indigenous. | C4: Workday Delivered | D4: Single instance | E4: Aboriginal/Indigenous Identification Selection | G4: Basic Bio | H4: Default Areas
A5: Aboriginal/Indigenous Identification Details | B5: The aboriginal/indigenous identification values for a person. | C5: Workday Delivered | D5: Multi-instance | E5: Aboriginal/Indigenous Identification Details | G5: Basic Bio | H5: Default Areas
A6: ABS CF EE Annual Work Period is F10 | C6: Calculated | D6: Single instance | E6: Worker | G6: Uncategorized | H6: Calculation Engine (Payroll/Absence)
A7: ABS CF EE Total FTE (Max 1 FTE) | C7: Calculated | D7: Numeric | G7: Uncategorized | H7: Default Areas
A8: ABS CF LRV Worker is Absence Administrator or Partner | C8: Calculated | D8: Boolean | G8: Security | H8: Calculation Engine (Payroll/Absence)
A9: ABS CF TF Total Blended FTE > 1 | C9: Calculated | D9: Boolean | G9: Leave of Absence | H9: Calculation Engine (Payroll/Absence)
A10: ABS CF Worker AWP is F10 | C10: Calculated | D10: Boolean | G10: Uncategorized | H10: Calculation Engine (Payroll/Absence)
A11: ABS CF Worker's FTE * 1040 | C11: Calculated | D11: Numeric | G11: Uncategorized | H11: Default Areas
A12: ABS CF Worker's FTE * 480 | C12: Calculated | D12: Numeric | G12: Uncategorized | H12: Default Areas
A13: Absence Case Event | B13: Returns Absence Case Events For Worker. | C13: Workday Delivered | D13: Multi-instance | E13: Absence Case Event | G13: Worker | H13: Default Areas
A14: Absence Occurrences for Worker in Date Range | B14: The absence occurrences for the worker within the date range. Workday groups absences that occur on either side of nonworking days into 1 consecutive absence. | C14: Workday Delivered | D14: Multi-instance | E14: Absence Occurrence | F14: Absence Occurrence Units (Hours) | G14: Time Off | H14: Default Areas
A15: ACA IRS 1094-C Reporting - Included in Total Employee Count for August | B15: This CRF is specific for ACA IRS Reporting. Returns True if the worker was included in the most recent calculation of 1094-C Total Employee counts for the month of August. Uses Entry Moment of when the calculate job (Calculate 1094-C Total and Full Time Employee Counts By Month) was run. | C15: Workday Delivered | D15: Boolean | F15: Month | G15: ACA IRS Reporting | H15: Default Areas
A16: ACA IRS 1094-C Reporting - Included in Total Employee Count for February | B16: This CRF is specific for ACA IRS Reporting. Returns True if the worker was included in the most recent calculation of 1094-C Total Employee counts for the month of February. Uses Entry Moment of when the calculate job (Calculate 1094-C Total and Full Time Employee Counts By Month) was run. | C16: Workday Delivered | D16: Boolean | F16: Month | G16: ACA IRS Reporting | H16: Default Areas
A17: ACA IRS 1094-C Reporting - Included in Total Employee Count for January | B17: This CRF is specific for ACA IRS Reporting. Returns True if the worker was included in the most recent calculation of 1094-C Total Employee counts for the month of January. Uses Entry Moment of when the calculate job (Calculate 1094-C Total and Full Time Employee Counts By Month) was run. | C17: Workday Delivered | D17: Boolean | F17: Month | G17: ACA IRS Reporting | H17: Default Areas
A18: ACA IRS 1094-C Reporting - Included in Total Employee Count for July | B18: This CRF is specific for ACA IRS Reporting. Returns True if the worker was included in the most recent calculation of 1094-C Total Employee counts for the month of July. Uses Entry Moment of when the calculate job (Calculate 1094-C Total and Full Time Employee Counts By Month) was run. | C18: Workday Delivered | D18: Boolean | F18: Month | G18: ACA IRS Reporting | H18: Default Areas
A19: ACA IRS 1094-C Reporting - Included in Total Employee Count for June | B19: This CRF is specific for ACA IRS Reporting. Returns True if the worker was included in the most recent calculation of 1094-C Total Employee counts for the month of June. Uses Entry Moment of when the calculate job (Calculate 1094-C Total and Full Time Employee Counts By Month) was run. | C19: Workday Delivered | D19: Boolean | F19: Month | G19: ACA IRS Reporting | H19: Default Areas
A20: ACA IRS 1094-C Reporting - Included in Total Employee Count for March | B20: This CRF is specific for ACA IRS Reporting. Returns True if the worker was included in the most recent calculation of 1094-C Total Employee counts for the month of March. Uses Entry Moment of when the calculate job (Calculate 1094-C Total and Full Time Employee Counts By Month) was run. | C20: Workday Delivered | D20: Boolean | F20: Month | G20: ACA IRS Reporting | H20: Default Areas
A21: ACA IRS 1094-C Reporting - Included in Total Employee Count for May | B21: This CRF is specific for ACA IRS Reporting. Returns True if the worker was included in the most recent calculation of 1094-C Total Employee counts for the month of May. Uses Entry Moment of when the calculate job (Calculate 1094-C Total and Full Time Employee Counts By Month) was run. | C21: Workday Delivered | D21: Boolean | F21: Month | G21: ACA IRS Reporting | H21: Default Areas
A22: ACA IRS 1094-C Reporting - Included in Total Employee Count for April | B22: This CRF is specific for ACA IRS Reporting. Returns True if the worker was included in the most recent calculation of 1094-C Total Employee counts for the month of April. Uses Entry Moment of when the calculate job (Calculate 1094-C Total and Full Time Employee Counts By Month) was run. | C22: Workday Delivered | D22: Boolean | F22: Month | G22: ACA IRS Reporting | H22: Default Areas
A23: ACA IRS 1094-C Reporting - Included in Total Employee Count for December | B23: This CRF is specific for ACA IRS Reporting. Returns True if the worker was included in the most recent calculation of 1094-C Total Employee counts for the month of December. Uses Entry Moment of when the calculate job (Calculate 1094-C Total and Full Time Employee Counts By Month) was run. | C23: Workday Delivered | D23: Boolean | F23: Month | G23: ACA IRS Reporting | H23: Default Areas
A24: ACA IRS 1094-C Reporting - Included in Total Employee Count for November | B24: This CRF is specific for ACA IRS Reporting. Returns True if the worker was included in the most recent calculation of 1094-C Total Employee counts for the month of November. Uses Entry Moment of when the calculate job (Calculate 1094-C Total and Full Time Employee Counts By Month) was run. | C24: Workday Delivered | D24: Boolean | F24: Month | G24: ACA IRS Reporting | H24: Default Areas
A25: ACA IRS 1094-C Reporting - Included in Total Employee Count for October | B25: This CRF is specific for ACA IRS Reporting. Returns True if the worker was included in the most recent calculation of 1094-C Total Employee counts for the month of October. Uses Entry Moment of when the calculate job (Calculate 1094-C Total and Full Time Employee Counts By Month) was run. | C25: Workday Delivered | D25: Boolean | F25: Month | G25: ACA IRS Reporting | H25: Default Areas
A26: ACA IRS 1094-C Reporting - Included in Total Employee Count for September | B26: This CRF is specific for ACA IRS Reporting. Returns True if the worker was included in the most recent calculation of 1094-C Total Employee counts for the month of September. Uses Entry Moment of when the calculate job (Calculate 1094-C Total and Full Time Employee Counts By Month) was run. | C26: Workday Delivered | D26: Boolean | F26: Month | G26: ACA IRS Reporting | H26: Default Areas
... A38: ACA IRS 1094-C Reporting - Worker Included in Full Time Count for September | B38: This CRF is specific for ACA IRS Reporting. Returns True if the worker was included in the most recent calculation of 1094-C full time Employee counts for the month of September. Uses Entry Moment of when the calculate job (Calculate 1094-C Total and Full Time Employee Counts By Month) was run. | C38: Workday Delivered | D38: Boolean | F38: Month | G38: ACA IRS Reporting | H38: Default Areas
A39: ACA Measurement Period Worker History Instances | B39: Returns all the ACA Measurement Period Worker History records/instances for a given worker/employee. | C39: Workday Delivered | D39: Multi-instance | E39: ACA Measurement Period Worker History | G39: Benefits | H39: Default Areas
A40: ACA Worker Hours And Wages Instances | B40: Returns all the ACA Worker Hours And Wages records/instances imported (via EIB/Web Service) for a given worker/employee. | C40: Workday Delivered | D40: Multi-instance | E40: Affordable Care Act Worker Hours And Wages | G40: Benefits Eligibility | H40: Benefits Eligibility
A41: Academic Affiliate | B41: Returns the academic affiliate object for the member. | C41: Workday Delivered | D41: Single instance | E41: Academic Affiliate | G41: Committee Memberships | H41: Default Areas
A42: Academic Appointment Identifiers | B42: All Academic Appointment Identifiers from the worker's current Academic Appointments. The "effective date" can be specified to return data that is current as of that date. If not specified, the current date is used. | C42: Workday Delivered | D42: Multi-instance | E42: Appointment Identifier | G42: Academic Appointments | H42: Default Areas
A43: Academic Appointment Tenured | B43: Returns true if any of the Worker's current Academic Appointments have a status of Tenured. The "effective date" can be specified to return data that is current as of that date. If not specified, the current date is used. | C43: Workday Delivered | D43: Boolean | G43: Academic Appointments | H43: Default Areas
A44: Academic Appointment Titles | B44: Contains the Academic Appointments for the Worker. In Report Writer, this field will display the Title, instead of the default display for an Academic Appointment. The "effective date" can be specified to return data that is current as of that date. If not specified, the current date is used. | C44: Workday Delivered | D44: Multi-instance | E44: Academic Appointment | G44: Academic Appointments | H44: Default Areas
A45: Academic Appointments | B45: Contains all the Academic Appointments for a Worker, past, present, and future, for all Academic Appointment Threads. | C45: Workday Delivered | D45: Multi-instance | E45: Academic Appointment | G45: Academic Appointments | H45: Default Areas
A46: Academic Appointments With Sabbatical Program | B46: All current Academic Appointments with Academic Track that includes Sabbatical Program. The "effective date" can be specified to return data that is current as of that date. If not specified, the current date is used. | C46: Workday Delivered | D46: Multi-instance | E46: Academic Appointment | G46: Academic Appointments | H46: Benefits Eligibility
A47: Academic Level for Committee Candidate | B47: The Academic Level for the committee member candidate. | C47: Workday Delivered | D47: Multi-instance | E47: Academic Level | G47: Committee Candidates | H47: Default Areas
A48: Academic Rank for Committee Candidate | B48: Returns the Academic Rank, if it exists, for a committee member candidate. | C48: Workday Delivered | D48: Multi-instance | E48: Rank | G48: Committee Candidates | H48: Default Areas
A49: Academic Rank for Primary Academic Appointment | B49: The Academic Rank for the Worker's primary Academic Appointment. The primary flag is located on the appointment's Identifier. | C49: Workday Delivered | D49: Single instance | E49: Rank | G49: Academic Appointments | H49: Default Areas
A50: Academic Ranks | B50: All Academic Ranks from the worker's current Academic Appointments. The "effective date" can be specified to return data that is current as of that date. If not specified, the current date is used. | C50: Workday Delivered | D50: Multi-instance | E50: Rank | G50: Academic Appointments | H50: Benefits Eligibility
A51: Academic Tenure Date | B51: The date which the worker received academic tenure. If the date is specified in an Academic Appointment, that date is used. If that date is not specified, but the tenure date is specified in the Maintain Tenure Business Process (deprecated in W15), this date is used. | C51: Workday Delivered | D51: Date | G51: Employment | H51: Benefits Eligibility
A52: Academic Tenure Status for Committee Candidate | B52: Returns the academic Tenure Status, if it exists, for a committee member candidate. | C52: Workday Delivered | D52: Multi-instance | E52: Academic Tenure Status | G52: Committee Candidates | H52: Default Areas
A53: Academic Tenure Statuses | B53: All Academic Appointment Tenure Statuses from the worker's current Academic Appointments. The "effective date" can be specified to return data that is current as of that date. If not specified, the current date is used. | C53: Workday Delivered | D53: Multi-instance | E53: Academic Tenure Status | G53: Academic Appointments | H53: Default Areas
A54: Academic Tenure Track Start Date | B54: Returns the Track Start Date for the current Appointment. The value is the earliest Appointment Start Date for the Appointment Track or the Track Start Date override when it exists | C54: Workday Delivered | D54: Date | G54: Academic Appointments | H54: Default Areas
A55: Academic Track Type Categories | B55: All Academic Track Types from the worker's current Academic Appointments. The "effective date" can be specified to return data that is current as of that date. If not specified, the current date is used. | C55: Workday Delivered | D55: Multi-instance | E55: Track Type Category | G55: Academic Appointments | H55: Benefits Eligibility
A56: Academic Track Type Category for Primary Academic Appointment | B56: The Academic Track Type Category for the Worker's primary Academic Appointment. The primary flag is located on the appointment's Identifier. | C56: Workday Delivered | D56: Single instance | E56: Track Type Category | G56: Academic Appointments | H56: Default Areas
A57: Academic Track Type for Committee Candidate | B57: Returns the Track Type, if it exists, for a committee member candidate. | C57: Workday Delivered | D57: Multi-instance | E57: Track Type | G57: Committee Candidates | H57: Default Areas
A58: Academic Track Types | B58: All Academic Track Types from the worker's current Academic Appointments. The "effective date" can be specified to return data that is current as of that date. If not specified, the current date is used. | C58: Workday Delivered | D58: Multi-instance | E58: Track Type | G58: Academic Appointments | H58: Benefits Eligibility
A59: Academic Unit for Committee Candidate | B59: The Academic Units for a committee member candidate. | C59: Workday Delivered | D59: Multi-instance | E59: Academic Unit | G59: Committee Candidates | H59: Default Areas
A60: Academic Unit for Primary Academic Appointment | B60: The Academic Unit for the Worker's primary Academic Appointment. The primary flag is located on the appointment's Identifier. | C60: Workday Delivered | D60: Single instance | E60: Academic Unit | G60: Academic Appointments | H60: Default Areas
A61: Academic Unit Hierarchy for Committee Candidate | B61: The Academic Unit Hierarchies for a committee member candidate, only applicable for academic affiliates and workers with academic appointments. | C61: Workday Delivered | D61: Multi-instance | E61: Academic Unit Hierarchy | G61: Committee Candidates | H61: Default Areas
A62: Academic Unit related to Supervisory Organization | B62: Academic Unit for Worker Supervisory Organization | C62: Workday Delivered | D62: Single instance | E62: Academic Unit | G62: Academic | H62: Default Areas
A63: Academic Units | B63: All Academic Units for the Worker's current Academic Appointments. The "effective date" can be specified to return data that is current as of that date. If not specified, the current date is used. | C63: Workday Delivered | D63: Multi-instance | E63: Academic Unit | G63: Academic Appointments | H63: Securing Entity
A64: Account Posting Rule Condition Dimension | B64: Account Posting Rule Condition Dimension | C64: Workday Delivered | D64: Multi-instance | E64: Account Posting Rule Dimension | G64: Account Posting Rule | H64: Default Areas
A65: Account Posting Rule Condition Value | B65: Account Posting Rule Condition Value | C65: Workday Delivered | D65: Multi-instance | E65: Account Posting Rule Condition Value | G65: Account Posting Rule | H65: Default Areas
A66: Account Posting Rule Condition Value Detail | B66: Account Posting Rule Condition Value Detail | C66: Workday Delivered | D66: Multi-instance | E66: Account Posting Rule Condition Value | G66: Account Posting Rule | H66: Default Areas
... A81: Active Military Uniformed Service | B81: The Active Military Uniformed Service for the person. | C81: Workday Delivered | D81: Single instance | E81: Common Boolean Enumeration | G81: Skills and Experience | H81: Default Areas
A82: Active Military Uniformed Service (Locale Sensitive) | B82: The Active Military Uniformed Service for the person. The value is based on the localization setting for worker. | C82: Workday Delivered | D82: Single instance | E82: Common Boolean Enumeration | F82: Field Display Configurable [Nonsingular] | G82: Skills and Experience | H82: Default Areas
A83: Active Onboarding Plan Assignment For Candidate | B83: The onboarding plan assignment currently assigned to the person associated with this candidate. | C83: Workday Delivered | D83: Single instance | E83: Onboarding Plan Assignment | G83: Onboarding | H83: Report Writer
A84: Active Onboarding Plan Assignment For Role | B84: The onboarding plan assignment currently assigned to the person associated with this role. | C84: Workday Delivered | D84: Single instance | E84: Onboarding Plan Assignment | G84: Onboarding | H84: Report Writer
A85: Active Regions for Recruiting | B85: The active regions for recruiting used to secure the candidate. | C85: Workday Delivered | D85: Multi-instance | E85: Region for Recruiting | G85: Recruiting | H85: Default Areas
A86: Active Skills | B86: Returns all active skills for the worker. | C86: Workday Delivered | D86: Multi-instance | E86: Local Skill Item | G86: Skills and Experience | H86: Default Areas
A87: Active Status | B87: Returns 'Yes' if the worker is active as of the report date if provided; excludes workers who are on certain types of leave or who are terminated. | C87: Workday Delivered | D87: Boolean | F87: Report Writer Provided Top Level Effective Moment | G87: Job & Position | H87: Security Attribute - System User
A88: Active Status (Benefits) | B88: Returns the active status of the worker | C88: Workday Delivered | D88: Boolean | G88: Benefits Eligibility | H88: Benefits Eligibility
A89: Active Status (Date As Of) | B89: Returns 'Yes' if the worker is active as of the Date As Of calculated field. Excludes workers who are on certain types of leave or who are terminated. | C89: Workday Delivered | D89: Boolean | G89: Job & Position | H89: Default Areas | I89: Yes
A90: Active Status with Date | B90: The status of the worker including the effective date. | C90: Workday Delivered | D90: Single instance | E90: Active Status | G90: Employment | H90: Default Areas
A91: Active Unions as of Leave Start Date | B91: Returns the unions the worker is an active member as of the leave start date. | C91: Workday Delivered | D91: Multi-instance | E91: Union | G91: Leave of Absence | H91: Default Areas
A92: Active Unions as of Period End Date | B92: Returns the unions the worker is an active member as of period end date. | C92: Workday Delivered | D92: Multi-instance | E92: Union | G92: Time Off | H92: Calculation Engine (Payroll/Absence)
A93: Active Unions as of Period Start Date | B93: Returns the unions the worker is an active member as of period start date. | C93: Workday Delivered | D93: Multi-instance | E93: Union | G93: Time Off | H93: Calculation Engine (Payroll/Absence)
A94: Active Unions as of Processing Date | B94: The unions where the worker is an active member as of the processing date. | C94: Workday Delivered | D94: Multi-instance | E94: Union | G94: Payroll | H94: Calculation Engine (Payroll/Absence)
A95: Active Unions as of Sub-Period End Date | B95: Returns the unions the worker is an active member as of the Sub Period End Date, if Sub Period End Date is available; if not available it is as of the Period End Date. | C95: Workday Delivered | D95: Multi-instance | E95: Union | G95: Payroll | H95: Calculation Engine (Payroll/Absence)
A96: Activity | B96: Trended Record Type of Activity | C96: Workday Delivered | D96: Single instance | E96: Trended Record Type | G96: Uncategorized | H96: Default Areas
A97: Actual Hours Worked (All Periods/All Pay Components for Worker's Primary Job) for Last 12 Months | B97: Returns the sum of hours worked for all external Payroll actuals for the worker's primary job during the prior 12-month period (Current Moment minus 1 Year through Current Moment minus 1 Day). Note that when this field is used in context with a Leave of Absence or a Time Off request, the Current Moment represents the First Day of Leave, or the Time Off As-Of Date, as applicable. Otherwise, the Current Moment is "Today". | C97: Workday Delivered | D97: Numeric | F97: As Of | G97: Benefits Eligibility | H97: Benefits Eligibility
A98: Actual Hours Worked (All Periods/All Pay Components for Worker) for Last 12 Months | B98: Returns the sum of hours worked for all external Payroll actuals for the worker during the prior 12-month period (Current Moment minus 1 Year through Current Moment minus 1 Day). Note that when this field is used in context with a Leave of Absence or a Time Off request, the Current Moment represents the First Day of Leave, or the Time Off As-Of Date, as applicable. Otherwise, the Current Moment is "Today". | C98: Workday Delivered | D98: Numeric | F98: As Of | G98: Benefits Eligibility | H98: Benefits Eligibility
A99: Actual Hours Worked (All Periods/All Pay Components for Worker) for Last 12 Months (Benefit Jobs) | B99: Returns the sum of hours worked for all external Payroll actuals for the worker during the prior 12-month period (Current Moment minus 1 Year through Current Moment minus 1 Day). Note that when this field is used in context with a Leave of Absence or a Time Off request, the Current Moment represents the First Day of Leave, or the Time Off As-Of Date, as applicable. Otherwise, the Current Moment is "Today". This is based on Benefit Jobs. | C99: Workday Delivered | D99: Numeric | F99: As Of | G99: Benefits Eligibility | H99: Benefits Eligibility
A100: Actual Hours Worked (Completed Periods/All Pay Components for Worker's Primary Job) for Last 12 Months | B100: Returns the sum of hours worked for all external Payroll actuals that are associated with a completed payroll Period for the worker's primary job during the prior 12-month period (Current Moment minus 1 Year through Current Moment minus 1 Day). Note that when this field is used in context with a Leave of Absence or a Time Off request, the Current Moment represents the First Day of Leave, or the Time Off As-Of Date, as applicable. Otherwise, the Current Moment is "Today". | C100: Workday Delivered | D100: Numeric | F100: As Of | G100: Benefits Eligibility | H100: Benefits Eligibility
A101: Actual Hours Worked (Completed Periods/All Pay Components for Worker) for Last 12 Months | B101: Returns the sum of hours worked for all external Payroll actuals that are associated with a completed payroll Period for the worker during the prior 12-month period (Current Moment minus 1 Year through Current Moment minus 1 Day). Note that when this field is used in context with a Leave of Absence or a Time Off request, the Current Moment represents the First Day of Leave, or the Time Off As-Of Date, as applicable. Otherwise, the Current Moment is "Today". | C101: Workday Delivered | D101: Numeric | F101: As Of | G101: Benefits Eligibility | H101: Benefits Eligibility
A102: Actual Hours Worked (Completed Periods/All Pay Components for Worker) for Last 12 Months (Benefit Jobs) | B102: Returns the sum of hours worked for all external Payroll actuals that are associated with a completed payroll Period for the worker during the prior 12-month period (Current Moment minus 1 Year through Current Moment minus 1 Day). Note that when this field is used in context with a Leave of Absence or a Time Off request, the Current Moment represents the First Day of Leave, or the Time Off As-Of Date, as applicable. Otherwise, the Current Moment is "Today". Used for Benefits Eligibility. | C102: Workday Delivered | D102: Numeric | F102: As Of | G102: Benefits Eligibility | H102: Benefits Eligibility
A103: Ad Hoc Payment | B103: The ad hoc payment for the payee. | C103: Workday Delivered | D103: Multi-instance | E103: Ad Hoc Payment | G103: Payments | H103: Default Areas
A104: Adaptive Planning System Users for Assignable Role | B104: The system users (Workday accounts) of the workers assigned to the role for the organization. This report field only returns system users for workers with access to the Access Adaptive Planning domain. | C104: Workday Delivered | D104: Multi-instance | E104: Workday Account | F104: Assignable Role for Dimension Type | G104: Roles | H104: Default Areas
A105: Adaptive Planning System Users for Assignable Roles | B105: The system users (Workday accounts) of the workers assigned to the roles for the organization. This report field only returns system users for workers with access to the Access Adaptive Planning domain. | C105: Workday Delivered | D105: Multi-instance | E105: Workday Account | F105: Assignable Roles for Dimension Type | G105: Roles | H105: Default Areas
A106: Added By Originator | B106: Gets worker who originally added the candidate. | C106: Workday Delivered | D106: Single instance | E106: Worker | G106: Recruiting | H106: Default Areas
A107: Added Date | B107: This is the date on which the candidate was created. | C107: Workday Delivered | D107: Date | G107: Recruiting | H107: Default Areas
A108: Additional Benefits Elections | B108: Contains all additional benefits elections for an employee. This includes elections made in current and future enrollment periods. To return elections that the employee is currently enrolled in, filter on the elections where Currently Enrolled is true. Note that the rows and data returned associated with this field are "effective date" aware. Entering an effective date at run time will control what data is returned. | C108: Workday Delivered | D108: Multi-instance | E108: Additional Benefits Election | G108: Benefits | H108: Default Areas
A109: Additional Job Classifications | B109: The additional job classifications on an active ~worker’s~ primary position. | C109: Workday Delivered | D109: Multi-instance | E109: Job Classification | G109: Job & Position | H109: Default Areas
A110: Additional Job History - All | B110: Contains all additional job events for the worker that the processing person is able to view. The ability to view the event is based on the event's security policy. | C110: Workday Delivered | D110: Multi-instance | E110: Add Additional Job Event | G110: Staffing History | H110: Default Areas
A111: Additional Jobs | B111: Returns the additional jobs for a worker. | C111: Workday Delivered | D111: Multi-instance | E111: Position | G111: Job & Position | H111: Default Areas
A112: Additional Jobs - All | B112: All of the ~worker’s~ additional jobs. You can only use this report field on a custom data source. | C112: Workday Delivered | D112: Multi-instance | E112: Position | G112: Job & Position | H112: Custom Data Source
A113: Additional Jobs if Enabled | B113: Returns the additional jobs for a worker if Additional Jobs is enabled. Otherwise nothing is returned. | C113: Workday Delivered | D113: Multi-instance | E113: Position | G113: Job & Position | H113: Default Areas
A114: Additional Names | B114: Additional names for the worker. | C114: Workday Delivered | D114: Multi-instance | E114: Global Name Interface | G114: Name | H114: Default Areas
A115: Additional Nationalities (Worker) | B115: Contains the nationalities for which the Worker holds additional nationalities. | C115: Workday Delivered | D115: Multi-instance | E115: Country and Nationality | G115: Basic Bio | H115: Benefits Eligibility
A116: Additional Nationalities (Worker) - Locale Sensitive | B116: Indicates the additional nationality of the person. Returns value based on the localization setting for Worker | C116: Workday Delivered | D116: Multi-instance | E116: Country and Nationality | G116: Uncategorized | H116: Default Areas
A117: Addresses | B117: Returns all addresses including the default location address if a work address for the worker does not exist. | C117: Workday Delivered | D117: Multi-instance | E117: Address | G117: Address & Phone | H117: Default Areas
A118: Addresses - Local | B118: Returns all addresses that include local script, including the default location address if a work address for the worker does not exist. The addresses are displayed using local format. | C118: Workday Delivered | D118: Multi-instance | E118: Address | G118: Address & Phone | H118: Default Areas
A119: Addresses without Default Work Address | B119: Contains all the addresses of the worker. Does not include the default work address from the location of the worker's primary job. | C119: Workday Delivered | D119: Multi-instance | E119: Address | G119: Address & Phone | H119: Default Areas
A120: Adjustable Compensation Basis - Amount | B120: The adjustable compensation basis amount for an employee, where the adjustable compensation basis is the one used by the employee's primary compensation basis. The number is represented in the currency and frequency of the employee's compensation grade profile, or compensation grade if no compensation grade profile exists. | C120: Workday Delivered | D120: Currency | G120: Compensation | H120: Default Areas
A121: Age | B121: The worker's age. | C121: Workday Delivered | D121: Numeric | G121: Benefits Eligibility | H121: Benefits Eligibility | I121: Yes
A122: Age (Agent) | B122: The worker's age. | C122: Workday Delivered | D122: Text | G122: Basic Bio | H122: Default Areas
A123: Age Group | B123: Returns the age group for the worker. | C123: Workday Delivered | D123: Single instance | E123: Age Band Definition | G123: Basic Bio | H123: Default Areas | I123: Yes
A124: Age Group for Committee Candidate | B124: Returns the age group, if available, for a committee member candidate. | C124: Workday Delivered | D124: Single instance | E124: Age Band Definition | G124: Committee Candidates | H124: Default Areas
A125: Aggregate Thrift Savings Plan Elections Amount | B125: The aggregated dollar amount per pay period that the employee elects to have deducted for the Thrift Savings Plan (TSP). To return an accurate total amount per pay period, the Pay Frequency of the worker's pay group must align with the Frequency of the worker's benefit group. | C125: Workday Delivered | D125: Currency | G125: Benefits | H125: Default Areas
...
